Workbook

Sheet Assumptions
A1: Ford Motor Company (F) - Assumptions
A2: Blue cells on yellow are inputs. Columns C:E show the historical value of each driver for reference.
A4: Millions | C4: FY2023 | D4: FY2024 | E4: FY2025 | F4: 2026E | G4: 2027E | H4: 2028E | I4: 2029E | J4: 2030E
A6: Switches and single inputs (column C)
A7: Minimum cash balance | C7: 11678
A8: Revolver capacity | C8: 18726.7
A9: Interest on average balances (1 = average, 0 = beginning) | C9: 1
A10: Circuit breaker (1 = force beginning balances, no circularity) | C10: 0
A11: D&A basis (1 = % of beginning net PP&E, 0 = % of revenue) | C11: 1
A13: Forecast drivers (columns F:J)
A14: Revenue growth | B14: vs prior year | D14: 0.049951473 | E14: 0.012297829 | F14: -0.018875349 | G14: -0.021987814 | H14: -0.025100279 | I14: -0.026656512 | J14: -0.026656512
A15: Gross margin | B15: gross profit / revenue (COGS as reported) | C15: 0.091718646 | D15: 0.083819841 | E15: 0.0089711481 | F15: 0.041503212 | G15: 0.041503212 | H15: 0.041503212 | I15: 0.041503212 | J15: 0.041503212
A16: SG&A % of revenue | C16: 0.060740901 | D16: 0.05560781 | E16: 0.057933325 | F16: 0.068094012 | G16: 0.068094012 | H16: 0.068094012 | I16: 0.068094012 | J16: 0.068094012
A17: R&D % of revenue | C17: 0 | D17: 0 | E17: 0 | F17: 0 | G17: 0 | H17: 0 | I17: 0 | J17: 0
A18: Other operating items % of revenue | B18: incl. the D&A reclassification | C18: -0.037022322 | D18: -0.031714885 | E18: -0.075480464 | F18: -0.048072557 | G18: -0.048072557 | H18: -0.048072557 | I18: -0.048072557 | J18: -0.048072557
A19: D&A % of beginning net PP&E (or of revenue) | D19: 0.094317177 | E19: 0.21788054 | F19: 0.15609886 | G19: 0.15609886 | H19: 0.15609886 | I19: 0.15609886 | J19: 0.15609886
A20: Capex % of revenue | C20: 0.046744726 | D20: 0.04694257 | E20: 0.047071828 | F20: 0.046919708 | G20: 0.046919708 | H20: 0.046919708 | I20: 0.046919708 | J20: 0.046919708
A21: Tax rate on EBT | B21: no tax credit on losses | C21: -0.091252836 | D21: 0.18512374 | E21: 0.31005917 | F21: 0.18512374 | G21: 0.18512374 | H21: 0.18512374 | I21: 0.18512374 | J21: 0.18512374
A22: DSO (days, on revenue) | B22: AR = DSO/365 x revenue | C22: 128.49402 | D22: 131.35241 | E22: 125.7708 | F22: 133.53908 | G22: 133.53908 | H22: 133.53908 | I22: 133.53908 | J22: 133.53908
A23: DIO (days, on COGS) | B23: Inventory = DIO/365 x COGS | C23: 35.696927 | D23: 32.198028 | E23: 30.061508 | F23: 37.652154 | G23: 37.652154 | H23: 37.652154 | I23: 37.652154 | J23: 37.652154
A24: DPO (days, on COGS) | B24: AP = DPO/365 x COGS | C24: 59.282764 | D24: 51.961342 | E24: 50.759401 | F24: 49.001169 | G24: 49.001169 | H24: 49.001169 | I24: 49.001169 | J24: 49.001169
A25: Other current assets % of revenue | C25: 0.020619668 | D25: 0.024876751 | E25: 0.02769842 | F25: 0.02439828 | G25: 0.02439828 | H25: 0.02439828 | I25: 0.02439828 | J25: 0.02439828
A26: Other current liabilities % of revenue | C26: 0.14682929 | D26: 0.15017947 | E26: 0.16969888 | F26: 0.15556921 | G26: 0.15556921 | H26: 0.15556921 | I26: 0.15556921 | J26: 0.15556921
A27: Dividend payout (% of NI to common) | C27: 1.1490683 | D27: 0.53036231 | F27: 0.83971531 | G27: 0.83971531 | H27: 0.83971531 | I27: 0.83971531 | J27: 0.83971531
A28: Buybacks (% of NI to common) | C28: 0.077064642 | D28: 0.072461303 | F28: 0.074762973 | G28: 0.074762973 | H28: 0.074762973 | I28: 0.074762973 | J28: 0.074762973
A29: Additional buybacks (amount) | F29: 0 | G29: 0 | H29: 0 | I29: 0 | J29: 0
A30: NCI share of net income | B30: distributed to NCI holders | C30: -0.0041580042 | D30: 0.002544961 | E30: -0.0024503798 | F30: 0 | G30: 0 | H30: 0 | I30: 0 | J30: 0
A31: Other non-operating income (amount) | F31: 0 | G31: 0 | H31: 0 | I31: 0 | J31: 0
A32: Term debt issuance (amount) | F32: 0 | G32: 0 | H32: 0 | I32: 0 | J32: 0
A33: Term debt mandatory repayment (amount) | F33: 0 | G33: 0 | H33: 0 | I33: 0 | J33: 0
A34: Interest rate on term debt | F34: 0.02283285 | G34: 0.02283285 | H34: 0.02283285 | I34: 0.02283285 | J34: 0.02283285
A35: Interest rate on cash & ST investments | F35: 0.039005291 | G35: 0.039005291 | H35: 0.039005291 | I35: 0.039005291 | J35: 0.039005291
A36: Interest rate on revolver | F36: 0.03783285 | G36: 0.03783285 | H36: 0.03783285 | I36: 0.03783285 | J36: 0.03783285

Sheet Income Statement
A1: Ford Motor Company (F) - Income Statement
A2: Historical columns: reported data. Forecast columns: formulas.
A4: Millions | C4: FY2023 | D4: FY2024 | E4: FY2025 | F4: 2026E | G4: 2027E | H4: 2028E | I4: 2029E | J4: 2030E
A6: Operating
A7: Revenue | C7: 176191 | D7: 184992 | E7: 187267 | F7: =E7*(1+Assumptions!F14) -> 183732.27 | G7: =F7*(1+Assumptions!G14) -> 179692.4 | H7: =G7*(1+Assumptions!H14) -> 175182.07 | I7: =H7*(1+Assumptions!I14) -> 170512.33 | J7: =I7*(1+Assumptions!J14) -> 165967.06
A8: Cost of goods sold (-) | C8: 160031 | D8: 169486 | E8: 185587 | F8: =F7*(1-Assumptions!F15) -> 176106.79 | G8: =G7*(1-Assumptions!G15) -> 172234.59 | H8: =H7*(1-Assumptions!H15) -> 167911.45 | I8: =I7*(1-Assumptions!I15) -> 163435.52 | J8: =J7*(1-Assumptions!J15) -> 159078.9
A9: Gross profit | C9: 16160 | D9: 15506 | E9: 1680 | F9: =F7-F8 -> 7625.4793 | G9: =G7-G8 -> 7457.8117 | H9: =H7-H8 -> 7270.6185 | I9: =I7-I8 -> 7076.8092 | J9: =J7-J8 -> 6888.1662
A10: SG&A (-) | C10: 10702 | D10: 10287 | E10: 10849 | F10: =F7*Assumptions!F16 -> 12511.067 | G10: =G7*Assumptions!G16 -> 12235.976 | H10: =H7*Assumptions!H16 -> 11928.85 | I10: =I7*Assumptions!I16 -> 11610.868 | J10: =J7*Assumptions!J16 -> 11301.363
A11: R&D (-) | F11: =F7*Assumptions!F17 -> 0 | G11: =G7*Assumptions!G17 -> 0 | H11: =H7*Assumptions!H17 -> 0 | I11: =I7*Assumptions!I17 -> 0 | J11: =J7*Assumptions!J17 -> 0
A12: Other operating items / D&A reclassification (-) | C12: -6523 | D12: -5867 | E12: -14135 | F12: =F7*Assumptions!F18 -> -8832.48 | G12: =G7*Assumptions!G18 -> -8638.2731 | H12: =H7*Assumptions!H18 -> -8421.45 | I12: =I7*Assumptions!I18 -> -8196.9636 | J12: =J7*Assumptions!J18 -> -7978.4611
A13: EBITDA | C13: 11981 | D13: 11086 | E13: 4966 | F13: =F9-F10-F11-F12 -> 3946.892 | G13: =G9-G10-G11-G12 -> 3860.1084 | H13: =H9-H10-H11-H12 -> 3763.2186 | I13: =I9-I10-I11-I12 -> 3662.9043 | J13: =J9-J10-J11-J12 -> 3565.2641
A14: Depreciation & amortization (-) | C14: 6523 | D14: 5867 | E14: 14135 | F14: =Schedules!F9 -> 10275.676 | G14: =Schedules!G9 -> 10017.33 | H14: =Schedules!H9 -> 9769.7239 | I14: =Schedules!I9 -> 9527.7344 | J14: =Schedules!J9 -> 9289.3175
A15: Operating income (EBIT, as reported) | C15: 5458 | D15: 5219 | E15: -9169 | F15: =F13-F14 -> -6328.7837 | G15: =G13-G14 -> -6157.2219 | H15: =H13-H14 -> -6006.5053 | I15: =I13-I14 -> -5864.83 | J15: =J13-J14 -> -5724.0534
A17: Below operating income
A18: Interest expense - term debt (-) | C18: 1318 | D18: 1136 | E18: 1333 | F18: =Schedules!F33 -> 3729.4264 | G18: =Schedules!G33 -> 3729.4264 | H18: =Schedules!H33 -> 3729.4264 | I18: =Schedules!I33 -> 3729.4264 | J18: =Schedules!J33 -> 3729.4264
A19: Interest expense - revolver (-) | C19: 0 | D19: 0 | E19: 0 | F19: =Schedules!F34 -> 109.59555 | G19: =Schedules!G34 -> 347.3378 | H19: =Schedules!H34 -> 591.98446 | I19: =Schedules!I34 -> 708.48443 | J19: =Schedules!J34 -> 708.48443
A20: Interest income | C20: 1567 | D20: 1540 | E20: 1490 | F20: =Schedules!F35 -> 1273.4448 | G20: =Schedules!G35 -> 1045.6929 | H20: =Schedules!H35 -> 1032.7796 | I20: =Schedules!I35 -> 884.63512 | J20: =Schedules!J35 -> 610.58562
A21: Other non-operating income / (expense) | C21: -1740 | D21: 1610 | E21: -2818 | F21: =Assumptions!F31 -> 0 | G21: =Assumptions!G31 -> 0 | H21: =Assumptions!H31 -> 0 | I21: =Assumptions!I31 -> 0 | J21: =Assumptions!J31 -> 0
A22: Pre-tax income (EBT) | C22: 3967 | D22: 7233 | E22: -11830 | F22: =F15-F18-F19+F20+F21 -> -8894.3609 | G22: =G15-G18-G19+G20+G21 -> -9188.2932 | H22: =H15-H18-H19+H20+H21 -> -9295.1365 | I22: =I15-I18-I19+I20+I21 -> -9418.1057 | J22: =J15-J18-J19+J20+J21 -> -9551.3785
A23: Income tax (-) | C23: -362 | D23: 1339 | E23: -3668 | F23: =MAX(0,F22*Assumptions!F21) -> 0 | G23: =MAX(0,G22*Assumptions!G21) -> 0 | H23: =MAX(0,H22*Assumptions!H21) -> 0 | I23: =MAX(0,I22*Assumptions!I21) -> 0 | J23: =MAX(0,J22*Assumptions!J21) -> 0
A24: Discontinued operations & other (after tax) | C24: 0 | D24: 0 | E24: 0 | F24: =0 -> 0 | G24: =0 -> 0 | H24: =0 -> 0 | I24: =0 -> 0 | J24: =0 -> 0
A26: Net income
A27: Net income (consolidated) | C27: 4329 | D27: 5894 | E27: -8162 | F27: =F22-F23+F24 -> -8894.3609 | G27: =G22-G23+G24 -> -9188.2932 | H27: =H22-H23+H24 -> -9295.1365 | I27: =I22-I23+I24 -> -9418.1057 | J27: =J22-J23+J24 -> -9551.3785
A28: Attributable to NCI & preferred (-) | C28: -18 | D28: 15 | E28: 20 | F28: =F27*Assumptions!F30 -> 0 | G28: =G27*Assumptions!G30 -> 0 | H28: =H27*Assumptions!H30 -> 0 | I28: =I27*Assumptions!I30 -> 0 | J28: =J27*Assumptions!J30 -> 0
A29: Net income to common shareholders | C29: 4347 | D29: 5879 | E29: -8182 | F29: =F27-F28 -> -8894.3609 | G29: =G27-G28 -> -9188.2932 | H29: =H27-H28 -> -9295.1365 | I29: =I27-I28 -> -9418.1057 | J29: =J27-J28 -> -9551.3785

Sheet Balance Sheet
A1: Ford Motor Company (F) - Balance Sheet
A2: Cash comes only from the Cash Flow sheet; the balance check must be 0.
A4: Millions | C4: FY2023 | D4: FY2024 | E4: FY2025 | F4: 2026E | G4: 2027E | H4: 2028E | I4: 2029E | J4: 2030E
A6: Assets
A7: Cash & cash equivalents | C7: 24862 | D7: 22935 | E7: 23356 | F7: ='Cash Flow'!F37 -> 11678 | G7: ='Cash Flow'!G37 -> 11678 | H7: ='Cash Flow'!H37 -> 11015.87 | I7: ='Cash Flow'!I37 -> 4081.879 | J7: ='Cash Flow'!J37 -> -3036.0435
A8: Short-term investments | C8: 15309 | D8: 15413 | E8: 15131 | F8: =E8 -> 15131 | G8: =F8 -> 15131 | H8: =G8 -> 15131 | I8: =H8 -> 15131 | J8: =I8 -> 15131
A9: Accounts receivable | C9: 62026 | D9: 66573 | E9: 64528 | F9: =Assumptions!F22/365*'Income Statement'!F7 -> 67220.377 | G9: =Assumptions!G22/365*'Income Statement'!G7 -> 65742.348 | H9: =Assumptions!H22/365*'Income Statement'!H7 -> 64092.197 | I9: =Assumptions!I22/365*'Income Statement'!I7 -> 62383.722 | J9: =Assumptions!J22/365*'Income Statement'!J7 -> 60720.79
A10: Inventory | C10: 15651 | D10: 14951 | E10: 15285 | F10: =Assumptions!F23/365*'Income Statement'!F8 -> 18166.576 | G10: =Assumptions!G23/365*'Income Statement'!G8 -> 17767.132 | H10: =Assumptions!H23/365*'Income Statement'!H8 -> 17321.172 | I10: =Assumptions!I23/365*'Income Statement'!I8 -> 16859.45 | J10: =Assumptions!J23/365*'Income Statement'!J8 -> 16410.036
A11: Other current assets | C11: 3633 | D11: 4602 | E11: 5187 | F11: =Assumptions!F25*'Income Statement'!F7 -> 4482.7514 | G11: =Assumptions!G25*'Income Statement'!G7 -> 4384.1855 | H11: =Assumptions!H25*'Income Statement'!H7 -> 4274.1412 | I11: =Assumptions!I25*'Income Statement'!I7 -> 4160.2075 | J11: =Assumptions!J25*'Income Statement'!J7 -> 4049.3109
A12: Total current assets | C12: 121481 | D12: 124474 | E12: 123487 | F12: =SUM(F7:F11) -> 116678.7 | G12: =SUM(G7:G11) -> 114702.67 | H12: =SUM(H7:H11) -> 111834.38 | I12: =SUM(I7:I11) -> 102616.26 | J12: =SUM(J7:J11) -> 93275.093
A13: Gross PP&E | C13: 99734 | D13: 102135 | E13: 106270 | F13: =IF(ISNUMBER(E13),E13+Schedules!F8,"") -> 114890.66 | G13: =IF(ISNUMBER(F13),F13+Schedules!G8,"") -> 123321.78 | H13: =IF(ISNUMBER(G13),G13+Schedules!H8,"") -> 131541.27 | I13: =IF(ISNUMBER(H13),H13+Schedules!I8,"") -> 139541.66 | J13: =IF(ISNUMBER(I13),I13+Schedules!J8,"") -> 147328.79
A14: Accumulated depreciation (-) | C14: 37529 | D14: 37260 | E14: 40442 | F14: =IF(ISNUMBER(E14),E14+Schedules!F9,"") -> 50717.676 | G14: =IF(ISNUMBER(F14),F14+Schedules!G9,"") -> 60735.006 | H14: =IF(ISNUMBER(G14),G14+Schedules!H9,"") -> 70504.73 | I14: =IF(ISNUMBER(H14),H14+Schedules!I9,"") -> 80032.464 | J14: =IF(ISNUMBER(I14),I14+Schedules!J9,"") -> 89321.782
A15: Net PP&E | C15: 62205 | D15: 64875 | E15: 65828 | F15: =Schedules!F10 -> 64172.989 | G15: =Schedules!G10 -> 62586.773 | H15: =Schedules!H10 -> 61036.541 | I15: =Schedules!I10 -> 59509.195 | J15: =Schedules!J10 -> 58007.004
A16: Other non-current assets | C16: 89624 | D16: 95847 | E16: 99845 | F16: =E16 -> 99845 | G16: =F16 -> 99845 | H16: =G16 -> 99845 | I16: =H16 -> 99845 | J16: =I16 -> 99845
A17: TOTAL ASSETS | C17: 273310 | D17: 285196 | E17: 289160 | F17: =F12+F15+F16 -> 280696.69 | G17: =G12+G15+G16 -> 277134.44 | H17: =H12+H15+H16 -> 272715.92 | I17: =I12+I15+I16 -> 261970.45 | J17: =J12+J15+J16 -> 251127.1
A19: Liabilities
A20: Accounts payable | C20: 25992 | D20: 24128 | E20: 25809 | F20: =Assumptions!F24/365*'Income Statement'!F8 -> 23642.298 | G20: =Assumptions!G24/365*'Income Statement'!G8 -> 23122.455 | H20: =Assumptions!H24/365*'Income Statement'!H8 -> 22542.075 | I20: =Assumptions!I24/365*'Income Statement'!I8 -> 21941.182 | J20: =Assumptions!J24/365*'Income Statement'!J8 -> 21356.307
A21: Other current liabilities | C21: 25870 | D21: 27782 | E21: 31779 | F21: =Assumptions!F26*'Income Statement'!F7 -> 28583.085 | G21: =Assumptions!G26*'Income Statement'!G7 -> 27954.605 | H21: =Assumptions!H26*'Income Statement'!H7 -> 27252.937 | I21: =Assumptions!I26*'Income Statement'!I7 -> 26526.469 | J21: =Assumptions!J26*'Income Statement'!J7 -> 25819.365
A22: Revolver | C22: 0 | D22: 0 | E22: 0 | F22: =Schedules!F29 -> 5793.6713 | G22: =Schedules!G29 -> 12568.033 | H22: =Schedules!H29 -> 18726.7 | I22: =Schedules!I29 -> 18726.7 | J22: =Schedules!J29 -> 18726.7
A23: Current liabilities (excl. term debt) | C23: 51862 | D23: 51910 | E23: 57588 | F23: =SUM(F20:F22) -> 58019.054 | G23: =SUM(G20:G22) -> 63645.093 | H23: =SUM(H20:H22) -> 68521.712 | I23: =SUM(I20:I22) -> 67194.351 | J23: =SUM(J20:J22) -> 65902.372
A24: Term debt (incl. current portion) | C24: 149231 | D24: 158522 | E24: 163336 | F24: =Schedules!F16 -> 163336 | G24: =Schedules!G16 -> 163336 | H24: =Schedules!H16 -> 163336 | I24: =Schedules!I16 -> 163336 | J24: =Schedules!J16 -> 163336
A25: Other non-current liabilities | C25: 29419 | D25: 29906 | E25: 32256 | F25: =E25 -> 32256 | G25: =F25 -> 32256 | H25: =G25 -> 32256 | I25: =H25 -> 32256 | J25: =I25 -> 32256
A26: TOTAL LIABILITIES | C26: 230512 | D26: 240338 | E26: 253180 | F26: =F23+F24+F25 -> 253611.05 | G26: =G23+G24+G25 -> 259237.09 | H26: =H23+H24+H25 -> 264113.71 | I26: =I23+I24+I25 -> 262786.35 | J26: =J23+J24+J25 -> 261494.37
A28: Equity
A29: Common stock & APIC | C29: 23170 | D29: 23544 | E29: 23964 | F29: =E29 -> 23964 | G29: =F29 -> 23964 | H29: =G29 -> 23964 | I29: =H29 -> 23964 | J29: =I29 -> 23964
A30: Retained earnings | C30: 31029 | D30: 33740 | E30: 22508 | F30: =E30+'Income Statement'!F29+'Cash Flow'!F27 -> 13613.639 | G30: =F30+'Income Statement'!G29+'Cash Flow'!G27 -> 4425.346 | H30: =G30+'Income Statement'!H29+'Cash Flow'!H27 -> -4869.7905 | I30: =H30+'Income Statement'!I29+'Cash Flow'!I27 -> -14287.896 | J30: =I30+'Income Statement'!J29+'Cash Flow'!J27 -> -23839.275
A31: Treasury stock (-) | C31: 2384 | D31: 2810 | E31: 2810 | F31: =E31-'Cash Flow'!F28 -> 2810 | G31: =F31-'Cash Flow'!G28 -> 2810 | H31: =G31-'Cash Flow'!H28 -> 2810 | I31: =H31-'Cash Flow'!I28 -> 2810 | J31: =I31-'Cash Flow'!J28 -> 2810
A32: AOCI & other equity | C32: -9042 | D32: -9639 | E32: -7710 | F32: =E32 -> -7710 | G32: =F32 -> -7710 | H32: =G32 -> -7710 | I32: =H32 -> -7710 | J32: =I32 -> -7710
A33: Shareholders' equity | C33: 42773 | D33: 44835 | E33: 35952 | F33: =F29+F30-F31+F32 -> 27057.639 | G33: =G29+G30-G31+G32 -> 17869.346 | H33: =H29+H30-H31+H32 -> 8574.2095 | I33: =I29+I30-I31+I32 -> -843.89625 | J33: =J29+J30-J31+J32 -> -10395.275
A34: Non-controlling interests | C34: 25 | D34: 23 | E34: 28 | F34: =E34+'Income Statement'!F28+'Cash Flow'!F29 -> 28 | G34: =F34+'Income Statement'!G28+'Cash Flow'!G29 -> 28 | H34: =G34+'Income Statement'!H28+'Cash Flow'!H29 -> 28 | I34: =H34+'Income Statement'!I28+'Cash Flow'!I29 -> 28 | J34: =I34+'Income Statement'!J28+'Cash Flow'!J29 -> 28
A35: TOTAL EQUITY | C35: 42798 | D35: 44858 | E35: 35980 | F35: =F33+F34 -> 27085.639 | G35: =G33+G34 -> 17897.346 | H35: =H33+H34 -> 8602.2095 | I35: =I33+I34 -> -815.89625 | J35: =J33+J34 -> -10367.275
A36: TOTAL LIABILITIES & EQUITY | C36: 273310 | D36: 285196 | E36: 289160 | F36: =F26+F35 -> 280696.69 | G36: =G26+G35 -> 277134.44 | H36: =H26+H35 -> 272715.92 | I36: =I26+I35 -> 261970.45 | J36: =J26+J35 -> 251127.1
A38: Check
A39: Balance check (A - L - E) | C39: =ROUND(C17-C36,6) -> 0 | D39: =ROUND(D17-D36,6) -> 0 | E39: =ROUND(E17-E36,6) -> 0 | F39: =ROUND(F17-F36,6) -> 0 | G39: =ROUND(G17-G36,6) -> 0 | H39: =ROUND(H17-H36,6) -> 0 | I39: =ROUND(I17-I36,6) -> 0 | J39: =ROUND(J17-J36,6) -> 0

Sheet Cash Flow
A1: Ford Motor Company (F) - Cash Flow
A2: Indirect method. Historical columns: reported, with disclosed 'other' lines.
A4: Millions | C4: FY2023 | D4: FY2024 | E4: FY2025 | F4: 2026E | G4: 2027E | H4: 2028E | I4: 2029E | J4: 2030E
A6: Operating activities
A7: Net income (consolidated) | C7: 4329 | D7: 5894 | E7: -8162 | F7: ='Income Statement'!F27 -> -8894.3609 | G7: ='Income Statement'!G27 -> -9188.2932 | H7: ='Income Statement'!H27 -> -9295.1365 | I7: ='Income Statement'!I27 -> -9418.1057 | J7: ='Income Statement'!J27 -> -9551.3785
A8: Depreciation & amortization | C8: 6523 | D8: 5867 | E8: 14135 | F8: ='Income Statement'!F14 -> 10275.676 | G8: ='Income Statement'!G14 -> 10017.33 | H8: ='Income Statement'!H14 -> 9769.7239 | I8: ='Income Statement'!I14 -> 9527.7344 | J8: ='Income Statement'!J14 -> 9289.3175
A9: (Increase) / decrease in receivables | F9: ='Balance Sheet'!E9-'Balance Sheet'!F9 -> -2692.377 | G9: ='Balance Sheet'!F9-'Balance Sheet'!G9 -> 1478.0291 | H9: ='Balance Sheet'!G9-'Balance Sheet'!H9 -> 1650.1513 | I9: ='Balance Sheet'!H9-'Balance Sheet'!I9 -> 1708.4744 | J9: ='Balance Sheet'!I9-'Balance Sheet'!J9 -> 1662.9324
A10: (Increase) / decrease in inventory | F10: ='Balance Sheet'!E10-'Balance Sheet'!F10 -> -2881.5755 | G10: ='Balance Sheet'!F10-'Balance Sheet'!G10 -> 399.44328 | H10: ='Balance Sheet'!G10-'Balance Sheet'!H10 -> 445.95998 | I10: ='Balance Sheet'!H10-'Balance Sheet'!I10 -> 461.72203 | J10: ='Balance Sheet'!I10-'Balance Sheet'!J10 -> 449.41413
A11: (Increase) / decrease in other current assets | F11: ='Balance Sheet'!E11-'Balance Sheet'!F11 -> 704.24865 | G11: ='Balance Sheet'!F11-'Balance Sheet'!G11 -> 98.565903 | H11: ='Balance Sheet'!G11-'Balance Sheet'!H11 -> 110.04428 | I11: ='Balance Sheet'!H11-'Balance Sheet'!I11 -> 113.93369 | J11: ='Balance Sheet'!I11-'Balance Sheet'!J11 -> 110.89662
A12: Increase / (decrease) in payables | F12: ='Balance Sheet'!F20-'Balance Sheet'!E20 -> -2166.7024 | G12: ='Balance Sheet'!G20-'Balance Sheet'!F20 -> -519.84244 | H12: ='Balance Sheet'!H20-'Balance Sheet'!G20 -> -580.38008 | I12: ='Balance Sheet'!I20-'Balance Sheet'!H20 -> -600.89309 | J12: ='Balance Sheet'!J20-'Balance Sheet'!I20 -> -584.87537
A13: Increase / (decrease) in other current liabilities | F13: ='Balance Sheet'!F21-'Balance Sheet'!E21 -> -3195.9153 | G13: ='Balance Sheet'!G21-'Balance Sheet'!F21 -> -628.47955 | H13: ='Balance Sheet'!H21-'Balance Sheet'!G21 -> -701.66839 | I13: ='Balance Sheet'!I21-'Balance Sheet'!H21 -> -726.46823 | J13: ='Balance Sheet'!J21-'Balance Sheet'!I21 -> -707.10312
A14: Change in working capital | C14: 1163 | D14: 1656 | E14: 12843 | F14: =SUM(F9:F13) -> -10232.322 | G14: =SUM(G9:G13) -> 827.71634 | H14: =SUM(H9:H13) -> 924.10707 | I14: =SUM(I9:I13) -> 956.7688 | J14: =SUM(J9:J13) -> 931.26468
A15: Other operating items (reported) | C15: 2903 | D15: 2006 | E15: 2466 | F15: =0 -> 0 | G15: =0 -> 0 | H15: =0 -> 0 | I15: =0 -> 0 | J15: =0 -> 0
A16: Cash from operations (CFO) | C16: 14918 | D16: 15423 | E16: 21282 | F16: =F7+F8+F14+F15 -> -8851.0068 | G16: =G7+G8+G14+G15 -> 1656.7535 | H16: =H7+H8+H14+H15 -> 1398.6944 | I16: =I7+I8+I14+I15 -> 1066.3975 | J16: =J7+J8+J14+J15 -> 669.2036
A18: Investing activities
A19: Capital expenditure | C19: -8236 | D19: -8684 | E19: -8815 | F19: =-Schedules!F8 -> -8620.6645 | G19: =-Schedules!G8 -> -8431.1149 | H19: =-Schedules!H8 -> -8219.4916 | I19: =-Schedules!I8 -> -8000.3886 | J19: =-Schedules!J8 -> -7787.1261
A20: Other investing (reported) | C20: -9392 | D20: -15686 | E20: -9234 | F20: =0 -> 0 | G20: =0 -> 0 | H20: =0 -> 0 | I20: =0 -> 0 | J20: =0 -> 0
A21: Cash from investing (CFI) | C21: -17628 | D21: -24370 | E21: -18049 | F21: =F19+F20 -> -8620.6645 | G21: =G19+G20 -> -8431.1149 | H21: =H19+H20 -> -8219.4916 | I21: =I19+I20 -> -8000.3886 | J21: =J19+J20 -> -7787.1261
A23: Financing activities
A24: Term debt issued | C24: 51659 | D24: 57312 | E24: 49688 | F24: =Schedules!F14 -> 0 | G24: =Schedules!G14 -> 0 | H24: =Schedules!H14 -> 0 | I24: =Schedules!I14 -> 0 | J24: =Schedules!J14 -> 0
A25: Term debt repaid | C25: -41965 | D25: -45680 | E25: -50303 | F25: =-Schedules!F15 -> 0 | G25: =-Schedules!G15 -> 0 | H25: =-Schedules!H15 -> 0 | I25: =-Schedules!I15 -> 0 | J25: =-Schedules!J15 -> 0
A26: Revolver draw / (repayment) | C26: 0 | D26: 0 | E26: 0 | F26: =Schedules!F27-Schedules!F28 -> 5793.6713 | G26: =Schedules!G27-Schedules!G28 -> 6774.3614 | H26: =Schedules!H27-Schedules!H28 -> 6158.6673 | I26: =Schedules!I27-Schedules!I28 -> 0 | J26: =Schedules!J27-Schedules!J28 -> 0
A27: Dividends | C27: -4995 | D27: -3118 | E27: -2989 | F27: =-Assumptions!F27*MAX(0,'Income Statement'!F29) -> 0 | G27: =-Assumptions!G27*MAX(0,'Income Statement'!G29) -> 0 | H27: =-Assumptions!H27*MAX(0,'Income Statement'!H29) -> 0 | I27: =-Assumptions!I27*MAX(0,'Income Statement'!I29) -> 0 | J27: =-Assumptions!J27*MAX(0,'Income Statement'!J29) -> 0
A28: Share buybacks | C28: -335 | D28: -426 | E28: 0 | F28: =-(Assumptions!F28*MAX(0,'Income Statement'!F29)+Assumptions!F29) -> 0 | G28: =-(Assumptions!G28*MAX(0,'Income Statement'!G29)+Assumptions!G29) -> 0 | H28: =-(Assumptions!H28*MAX(0,'Income Statement'!H29)+Assumptions!H29) -> 0 | I28: =-(Assumptions!I28*MAX(0,'Income Statement'!I29)+Assumptions!I29) -> 0 | J28: =-(Assumptions!J28*MAX(0,'Income Statement'!J29)+Assumptions!J29) -> 0
A29: Distributions to NCI | C29: 0 | D29: 0 | E29: 0 | F29: =-MAX(0,'Income Statement'!F28) -> 0 | G29: =-MAX(0,'Income Statement'!G28) -> 0 | H29: =-MAX(0,'Income Statement'!H28) -> 0 | I29: =-MAX(0,'Income Statement'!I28) -> 0 | J29: =-MAX(0,'Income Statement'!J28) -> 0
A30: Other financing (reported) | C30: -1780 | D30: -603 | E30: 399 | F30: =0 -> 0 | G30: =0 -> 0 | H30: =0 -> 0 | I30: =0 -> 0 | J30: =0 -> 0
A31: Cash from financing (CFF) | C31: 2584 | D31: 7485 | E31: -3205 | F31: =SUM(F24:F30) -> 5793.6713 | G31: =SUM(G24:G30) -> 6774.3614 | H31: =SUM(H24:H30) -> 6158.6673 | I31: =SUM(I24:I30) -> 0 | J31: =SUM(J24:J30) -> 0
A33: Cash
A34: FX & other (reported) | C34: -104 | D34: -458 | E34: 532 | F34: =0 -> 0 | G34: =0 -> 0 | H34: =0 -> 0 | I34: =0 -> 0 | J34: =0 -> 0
A35: Net change in cash | C35: -230 | D35: -1920 | E35: 560 | F35: =F16+F21+F31+F34 -> -11678 | G35: =G16+G21+G31+G34 -> 0 | H35: =H16+H21+H31+H34 -> -662.12985 | I35: =I16+I21+I31+I34 -> -6933.9911 | J35: =J16+J21+J31+J34 -> -7117.9225
A36: Beginning cash | C36: 25340 | D36: 25110 | E36: 23190 | F36: ='Balance Sheet'!E7 -> 23356 | G36: ='Balance Sheet'!F7 -> 11678 | H36: ='Balance Sheet'!G7 -> 11678 | I36: ='Balance Sheet'!H7 -> 11015.87 | J36: ='Balance Sheet'!I7 -> 4081.879
A37: Ending cash | C37: 25110 | D37: 23190 | E37: 23750 | F37: =F36+F35 -> 11678 | G37: =G36+G35 -> 11678 | H37: =H36+H35 -> 11015.87 | I37: =I36+I35 -> 4081.879 | J37: =J36+J35 -> -3036.0435
A39: Memo
A40: Free cash flow (CFO - capex) | C40: 6682 | D40: 6739 | E40: 12467 | F40: =F16+F19 -> -17471.671 | G40: =G16+G19 -> -6774.3614 | H40: =H16+H19 -> -6820.7971 | I40: =I16+I19 -> -6933.9911 | J40: =J16+J19 -> -7117.9225
A42: Historical ending cash is the cash-flow statement figure, which can include restricted cash; the forecast starts from balance-sheet cash.

Sheet Schedules
A1: Ford Motor Company (F) - Schedules
A2: PP&E, term debt, revolver and interest. Interest uses average balances unless the circuit breaker is on.
A4: Millions | C4: FY2023 | D4: FY2024 | E4: FY2025 | F4: 2026E | G4: 2027E | H4: 2028E | I4: 2029E | J4: 2030E
A6: PP&E roll-forward
A7: Beginning net PP&E | F7: ='Balance Sheet'!E15 -> 65828 | G7: ='Balance Sheet'!F15 -> 64172.989 | H7: ='Balance Sheet'!G15 -> 62586.773 | I7: ='Balance Sheet'!H15 -> 61036.541 | J7: ='Balance Sheet'!I15 -> 59509.195
A8: Capex | C8: 8236 | D8: 8684 | E8: 8815 | F8: =Assumptions!F20*'Income Statement'!F7 -> 8620.6645 | G8: =Assumptions!G20*'Income Statement'!G7 -> 8431.1149 | H8: =Assumptions!H20*'Income Statement'!H7 -> 8219.4916 | I8: =Assumptions!I20*'Income Statement'!I7 -> 8000.3886 | J8: =Assumptions!J20*'Income Statement'!J7 -> 7787.1261
A9: Depreciation & amortization | C9: 6523 | D9: 5867 | E9: 14135 | F9: =MIN(MAX(0,IF(Assumptions!$C$11=1,F7*Assumptions!F19,'Income Statement'!F7*Assumptions!F19)),MAX(0,F7+F8)) -> 10275.676 | G9: =MIN(MAX(0,IF(Assumptions!$C$11=1,G7*Assumptions!G19,'Income Statement'!G7*Assumptions!G19)),MAX(0,G7+G8)) -> 10017.33 | H9: =MIN(MAX(0,IF(Assumptions!$C$11=1,H7*Assumptions!H19,'Income Statement'!H7*Assumptions!H19)),MAX(0,H7+H8)) -> 9769.7239 | I9: =MIN(MAX(0,IF(Assumptions!$C$11=1,I7*Assumptions!I19,'Income Statement'!I7*Assumptions!I19)),MAX(0,I7+I8)) -> 9527.7344 | J9: =MIN(MAX(0,IF(Assumptions!$C$11=1,J7*Assumptions!J19,'Income Statement'!J7*Assumptions!J19)),MAX(0,J7+J8)) -> 9289.3175
A10: Ending net PP&E | C10: 62205 | D10: 64875 | E10: 65828 | F10: =F7+F8-F9 -> 64172.989 | G10: =G7+G8-G9 -> 62586.773 | H10: =H7+H8-H9 -> 61036.541 | I10: =I7+I8-I9 -> 59509.195 | J10: =J7+J8-J9 -> 58007.004
A12: Term debt
A13: Beginning term debt | F13: ='Balance Sheet'!E24 -> 163336 | G13: ='Balance Sheet'!F24 -> 163336 | H13: ='Balance Sheet'!G24 -> 163336 | I13: ='Balance Sheet'!H24 -> 163336 | J13: ='Balance Sheet'!I24 -> 163336
A14: Issuance | F14: =Assumptions!F32 -> 0 | G14: =Assumptions!G32 -> 0 | H14: =Assumptions!H32 -> 0 | I14: =Assumptions!I32 -> 0 | J14: =Assumptions!J32 -> 0
A15: Mandatory repayment (capped at balance) | F15: =MIN(Assumptions!F33,F13+F14) -> 0 | G15: =MIN(Assumptions!G33,G13+G14) -> 0 | H15: =MIN(Assumptions!H33,H13+H14) -> 0 | I15: =MIN(Assumptions!I33,I13+I14) -> 0 | J15: =MIN(Assumptions!J33,J13+J14) -> 0
A16: Ending term debt | C16: 149231 | D16: 158522 | E16: 163336 | F16: =F13+F14-F15 -> 163336 | G16: =G13+G14-G15 -> 163336 | H16: =H13+H14-H15 -> 163336 | I16: =I13+I14-I15 -> 163336 | J16: =J13+J14-J15 -> 163336
A18: Revolver
A19: Beginning revolver | F19: ='Balance Sheet'!E22 -> 0 | G19: ='Balance Sheet'!F22 -> 5793.6713 | H19: ='Balance Sheet'!G22 -> 12568.033 | I19: ='Balance Sheet'!H22 -> 18726.7 | J19: ='Balance Sheet'!I22 -> 18726.7
A20: Beginning cash | F20: ='Balance Sheet'!E7 -> 23356 | G20: ='Balance Sheet'!F7 -> 11678 | H20: ='Balance Sheet'!G7 -> 11678 | I20: ='Balance Sheet'!H7 -> 11015.87 | J20: ='Balance Sheet'!I7 -> 4081.879
A21: Cash from operations | F21: ='Cash Flow'!F16 -> -8851.0068 | G21: ='Cash Flow'!G16 -> 1656.7535 | H21: ='Cash Flow'!H16 -> 1398.6944 | I21: ='Cash Flow'!I16 -> 1066.3975 | J21: ='Cash Flow'!J16 -> 669.2036
A22: Cash from investing | F22: ='Cash Flow'!F21 -> -8620.6645 | G22: ='Cash Flow'!G21 -> -8431.1149 | H22: ='Cash Flow'!H21 -> -8219.4916 | I22: ='Cash Flow'!I21 -> -8000.3886 | J22: ='Cash Flow'!J21 -> -7787.1261
A23: Financing before revolver | F23: ='Cash Flow'!F24+'Cash Flow'!F25+'Cash Flow'!F27+'Cash Flow'!F28+'Cash Flow'!F29 -> 0 | G23: ='Cash Flow'!G24+'Cash Flow'!G25+'Cash Flow'!G27+'Cash Flow'!G28+'Cash Flow'!G29 -> 0 | H23: ='Cash Flow'!H24+'Cash Flow'!H25+'Cash Flow'!H27+'Cash Flow'!H28+'Cash Flow'!H29 -> 0 | I23: ='Cash Flow'!I24+'Cash Flow'!I25+'Cash Flow'!I27+'Cash Flow'!I28+'Cash Flow'!I29 -> 0 | J23: ='Cash Flow'!J24+'Cash Flow'!J25+'Cash Flow'!J27+'Cash Flow'!J28+'Cash Flow'!J29 -> 0
A24: Cash before revolver | F24: =F20+F21+F22+F23 -> 5884.3287 | G24: =G20+G21+G22+G23 -> 4903.6386 | H24: =H20+H21+H22+H23 -> 4857.2029 | I24: =I20+I21+I22+I23 -> 4081.879 | J24: =J20+J21+J22+J23 -> -3036.0435
A25: Minimum cash | F25: =Assumptions!$C$7 -> 11678 | G25: =Assumptions!$C$7 -> 11678 | H25: =Assumptions!$C$7 -> 11678 | I25: =Assumptions!$C$7 -> 11678 | J25: =Assumptions!$C$7 -> 11678
A26: Undrawn revolver capacity | F26: =MAX(0,Assumptions!$C$8-F19) -> 18726.7 | G26: =MAX(0,Assumptions!$C$8-G19) -> 12933.029 | H26: =MAX(0,Assumptions!$C$8-H19) -> 6158.6673 | I26: =MAX(0,Assumptions!$C$8-I19) -> 0 | J26: =MAX(0,Assumptions!$C$8-J19) -> 0
A27: Revolver draw | F27: =IF(F24<F25,MIN(F25-F24,F26),0) -> 5793.6713 | G27: =IF(G24<G25,MIN(G25-G24,G26),0) -> 6774.3614 | H27: =IF(H24<H25,MIN(H25-H24,H26),0) -> 6158.6673 | I27: =IF(I24<I25,MIN(I25-I24,I26),0) -> 0 | J27: =IF(J24<J25,MIN(J25-J24,J26),0) -> 0
A28: Revolver repayment | F28: =IF(F24<F25,0,MIN(F19,F24-F25)) -> 0 | G28: =IF(G24<G25,0,MIN(G19,G24-G25)) -> 0 | H28: =IF(H24<H25,0,MIN(H19,H24-H25)) -> 0 | I28: =IF(I24<I25,0,MIN(I19,I24-I25)) -> 0 | J28: =IF(J24<J25,0,MIN(J19,J24-J25)) -> 0
A29: Ending revolver | C29: 0 | D29: 0 | E29: 0 | F29: =F19+F27-F28 -> 5793.6713 | G29: =G19+G27-G28 -> 12568.033 | H29: =H19+H27-H28 -> 18726.7 | I29: =I19+I27-I28 -> 18726.7 | J29: =J19+J27-J28 -> 18726.7
A31: Interest (circular when average balances are used)
A32: Average balances in use (1 = yes) | F32: =IF(AND(Assumptions!$C$9=1,Assumptions!$C$10=0),1,0) -> 1 | G32: =IF(AND(Assumptions!$C$9=1,Assumptions!$C$10=0),1,0) -> 1 | H32: =IF(AND(Assumptions!$C$9=1,Assumptions!$C$10=0),1,0) -> 1 | I32: =IF(AND(Assumptions!$C$9=1,Assumptions!$C$10=0),1,0) -> 1 | J32: =IF(AND(Assumptions!$C$9=1,Assumptions!$C$10=0),1,0) -> 1
A33: Interest expense - term debt | F33: =Assumptions!F34*IF(F32=1,(F13+F16)/2,F13) -> 3729.4264 | G33: =Assumptions!G34*IF(G32=1,(G13+G16)/2,G13) -> 3729.4264 | H33: =Assumptions!H34*IF(H32=1,(H13+H16)/2,H13) -> 3729.4264 | I33: =Assumptions!I34*IF(I32=1,(I13+I16)/2,I13) -> 3729.4264 | J33: =Assumptions!J34*IF(J32=1,(J13+J16)/2,J13) -> 3729.4264
A34: Interest expense - revolver | F34: =Assumptions!F36*IF(F32=1,(F19+F29)/2,F19) -> 109.59555 | G34: =Assumptions!G36*IF(G32=1,(G19+G29)/2,G19) -> 347.3378 | H34: =Assumptions!H36*IF(H32=1,(H19+H29)/2,H19) -> 591.98446 | I34: =Assumptions!I36*IF(I32=1,(I19+I29)/2,I19) -> 708.48443 | J34: =Assumptions!J36*IF(J32=1,(J19+J29)/2,J19) -> 708.48443
A35: Interest income on cash & ST investments | F35: =Assumptions!F35*MAX(0,IF(F32=1,('Balance Sheet'!E7+'Balance Sheet'!E8+'Balance Sheet'!F7+'Balance Sheet'!F8)/2,'Balance Sheet'!E7+'Balance Sheet'!E8)) -> 1273.4448 | G35: =Assumptions!G35*MAX(0,IF(G32=1,('Balance Sheet'!F7+'Balance Sheet'!F8+'Balance Sheet'!G7+'Balance Sheet'!G8)/2,'Balance Sheet'!F7+'Balance Sheet'!F8)) -> 1045.6929 | H35: =Assumptions!H35*MAX(0,IF(H32=1,('Balance Sheet'!G7+'Balance Sheet'!G8+'Balance Sheet'!H7+'Balance Sheet'!H8)/2,'Balance Sheet'!G7+'Balance Sheet'!G8)) -> 1032.7796 | I35: =Assumptions!I35*MAX(0,IF(I32=1,('Balance Sheet'!H7+'Balance Sheet'!H8+'Balance Sheet'!I7+'Balance Sheet'!I8)/2,'Balance Sheet'!H7+'Balance Sheet'!H8)) -> 884.63512 | J35: =Assumptions!J35*MAX(0,IF(J32=1,('Balance Sheet'!I7+'Balance Sheet'!I8+'Balance Sheet'!J7+'Balance Sheet'!J8)/2,'Balance Sheet'!I7+'Balance Sheet'!I8)) -> 610.58562

Sheet Checks
A1: Ford Motor Company (F) - Checks
A2: Every forecast check must be 0 after recalculation.
A4: Millions | C4: FY2023 | D4: FY2024 | E4: FY2025 | F4: 2026E | G4: 2027E | H4: 2028E | I4: 2029E | J4: 2030E
A6: Integrity checks
A7: Balance check: assets - liabilities - equity | C7: ='Balance Sheet'!C39 -> 0 | D7: ='Balance Sheet'!D39 -> 0 | E7: ='Balance Sheet'!E39 -> 0 | F7: ='Balance Sheet'!F39 -> 0 | G7: ='Balance Sheet'!G39 -> 0 | H7: ='Balance Sheet'!H39 -> 0 | I7: ='Balance Sheet'!I39 -> 0 | J7: ='Balance Sheet'!J39 -> 0
A8: Cash: balance sheet - cash-flow ending cash | F8: =ROUND('Balance Sheet'!F7-'Cash Flow'!F37,6) -> 0 | G8: =ROUND('Balance Sheet'!G7-'Cash Flow'!G37,6) -> 0 | H8: =ROUND('Balance Sheet'!H7-'Cash Flow'!H37,6) -> 0 | I8: =ROUND('Balance Sheet'!I7-'Cash Flow'!I37,6) -> 0 | J8: =ROUND('Balance Sheet'!J7-'Cash Flow'!J37,6) -> 0
A9: Retained earnings roll-forward | F9: =ROUND('Balance Sheet'!F30-('Balance Sheet'!E30+'Income Statement'!F29+'Cash Flow'!F27),6) -> 0 | G9: =ROUND('Balance Sheet'!G30-('Balance Sheet'!F30+'Income Statement'!G29+'Cash Flow'!G27),6) -> 0 | H9: =ROUND('Balance Sheet'!H30-('Balance Sheet'!G30+'Income Statement'!H29+'Cash Flow'!H27),6) -> 0 | I9: =ROUND('Balance Sheet'!I30-('Balance Sheet'!H30+'Income Statement'!I29+'Cash Flow'!I27),6) -> 0 | J9: =ROUND('Balance Sheet'!J30-('Balance Sheet'!I30+'Income Statement'!J29+'Cash Flow'!J27),6) -> 0
A10: Net PP&E roll-forward | F10: =ROUND('Balance Sheet'!F15-('Balance Sheet'!E15-'Cash Flow'!F19-'Income Statement'!F14),6) -> 0 | G10: =ROUND('Balance Sheet'!G15-('Balance Sheet'!F15-'Cash Flow'!G19-'Income Statement'!G14),6) -> 0 | H10: =ROUND('Balance Sheet'!H15-('Balance Sheet'!G15-'Cash Flow'!H19-'Income Statement'!H14),6) -> 0 | I10: =ROUND('Balance Sheet'!I15-('Balance Sheet'!H15-'Cash Flow'!I19-'Income Statement'!I14),6) -> 0 | J10: =ROUND('Balance Sheet'!J15-('Balance Sheet'!I15-'Cash Flow'!J19-'Income Statement'!J14),6) -> 0
A11: Debt roll-forward (term + revolver) | F11: =ROUND(('Balance Sheet'!F24+'Balance Sheet'!F22)-('Balance Sheet'!E24+'Balance Sheet'!E22+'Cash Flow'!F24+'Cash Flow'!F25+'Cash Flow'!F26),6) -> 0 | G11: =ROUND(('Balance Sheet'!G24+'Balance Sheet'!G22)-('Balance Sheet'!F24+'Balance Sheet'!F22+'Cash Flow'!G24+'Cash Flow'!G25+'Cash Flow'!G26),6) -> 0 | H11: =ROUND(('Balance Sheet'!H24+'Balance Sheet'!H22)-('Balance Sheet'!G24+'Balance Sheet'!G22+'Cash Flow'!H24+'Cash Flow'!H25+'Cash Flow'!H26),6) -> 0 | I11: =ROUND(('Balance Sheet'!I24+'Balance Sheet'!I22)-('Balance Sheet'!H24+'Balance Sheet'!H22+'Cash Flow'!I24+'Cash Flow'!I25+'Cash Flow'!I26),6) -> 0 | J11: =ROUND(('Balance Sheet'!J24+'Balance Sheet'!J22)-('Balance Sheet'!I24+'Balance Sheet'!I22+'Cash Flow'!J24+'Cash Flow'!J25+'Cash Flow'!J26),6) -> 0
A13: Largest absolute check (all years) - must be 0 | C13: =MAX(MAX(C7:J7,C8:J8,C9:J9,C10:J10,C11:J11),-MIN(C7:J7,C8:J8,C9:J9,C10:J10,C11:J11)) -> 0
A15: Revolver capacity exhausted (cash below minimum)? | F15: =IF(Schedules!F24+Schedules!F27<Schedules!F25-0.005,"SHORTFALL","ok") -> ok | G15: =IF(Schedules!G24+Schedules!G27<Schedules!G25-0.005,"SHORTFALL","ok") -> ok | H15: =IF(Schedules!H24+Schedules!H27<Schedules!H25-0.005,"SHORTFALL","ok") -> SHORTFALL | I15: =IF(Schedules!I24+Schedules!I27<Schedules!I25-0.005,"SHORTFALL","ok") -> SHORTFALL | J15: =IF(Schedules!J24+Schedules!J27<Schedules!J25-0.005,"SHORTFALL","ok") -> SHORTFALL
A17: How the circularity works: interest depends on the average debt and cash balances, which depend on net income, which depends on interest. Excel solves it with iterative calculation (File > Options > Formulas > Enable iterative calculation, saved on in this file).
A18: If the file ever shows errors (#VALUE!, #REF!) spreading through the circular loop, set the circuit breaker on the Assumptions sheet to 1, let it recalculate, then set it back to 0.

Sheet Data Sources
A1: Data sources, mapping and warnings
A3: Source | B3: Yahoo Finance snapshot downloaded 2026-10-01
A5: Warnings and assumptions
A6: FY2023: cash-flow statement ending cash 25,110.0 differs from balance-sheet cash 24,862.0 by 248.0 (usually restricted cash or cash held for sale). The forecast starts from balance-sheet cash.
A7: FY2024: cash-flow statement ending cash 23,190.0 differs from balance-sheet cash 22,935.0 by 255.0 (usually restricted cash or cash held for sale). The forecast starts from balance-sheet cash.
A8: FY2025: cash-flow statement ending cash 23,750.0 differs from balance-sheet cash 23,356.0 by 394.0 (usually restricted cash or cash held for sale). The forecast starts from balance-sheet cash.
A9: Not reported by Yahoo (shown as n/a or 0): rd.
A10: Interest rate on debt from the history is only 0.8%: reported interest expense may exclude interest shown elsewhere (e.g. a finance arm's interest inside cost of sales). Review it.
A11: Minimum cash: 50% of the latest cash balance (assumption). Revolver capacity: 10% of latest revenue (assumption).
A12: 2028E: revolver capacity exhausted - cash is 662.1 below the minimum.
A13: 2029E: revolver capacity exhausted - cash is 7,596.1 below the minimum.
A14: 2030E: revolver capacity exhausted - cash is 14,714.0 below the minimum and negative.
A16: Model item | B16: Yahoo line used (FY2023) | C16: Yahoo line used (FY2024) | D16: Yahoo line used (FY2025)
A17: revenue | B17: Total Revenue | C17: Total Revenue | D17: Total Revenue
A18: cogs | B18: Cost Of Revenue | C18: Cost Of Revenue | D18: Cost Of Revenue
A19: gross_profit_reported | B19: Gross Profit | C19: Gross Profit | D19: Gross Profit
A20: sga | B20: Selling General And Administration | C20: Selling General And Administration | D20: Selling General And Administration
A21: rd | B21: (not reported) | C21: (not reported) | D21: (not reported)
A22: da | B22: Reconciled Depreciation | C22: Reconciled Depreciation | D22: Reconciled Depreciation
A23: ebit | B23: Operating Income | C23: Operating Income | D23: Operating Income
A24: interest_expense | B24: Interest Expense | C24: Interest Expense | D24: Interest Expense
A25: interest_income | B25: Interest Income | C25: Interest Income | D25: Interest Income
A26: ebt | B26: Pretax Income | C26: Pretax Income | D26: Pretax Income
A27: tax | B27: Tax Provision | C27: Tax Provision | D27: Tax Provision
... A66: nci | B66: Total Equity Gross Minority Interest - Stockholders Equity | C66: Total Equity Gross Minority Interest - Stockholders Equity | D66: Total Equity Gross Minority Interest - Stockholders Equity
