Workbook

Sheet Investment
A1: Investment Growth Model
A2: Yellow cells with blue numbers are inputs; everything else is a live formula. Rows were created for the chosen horizon; shortening it works, lengthening it needs a new export.
A3: Inputs | E3: Summary (live)
A4: Initial amount (t = 0) | C4: 10000 | E4: Final value (nominal) | F4: =INDEX($G$25:$G$384,C16) -> 914744.96
A5: Contribution / period | C5: 500 | E5: Final value in today's money (real) | F5: =INDEX($H$25:$H$384,C16) -> 436097.97
A6: Contributions per year p | C6: 12 | E6: Initial amount | F6: =C4 -> 10000
A7: Timing (0 end, 1 begin) | C7: 0 | E7: Total contributions | F7: =SUMIF($A$25:$A$384,"<="&$C$16,$D$25:$D$384) -> 285452.49
A8: Annual return (nominal) | C8: 0.07 | E8: Total invested | F8: =F6+F7 -> 295452.49
A9: Compounding / yr m | C9: 12 | E9: Gross growth | F9: =SUMIF($A$25:$A$384,"<="&$C$16,$E$25:$E$384) -> 619292.47
A10: Years | C10: 30 | E10: Tax on gains | F10: =SUMIF($A$25:$A$384,"<="&$C$16,$F$25:$F$384) -> 0
A11: Step-up per year | C11: 0.03 | E11: Growth after tax | F11: =F9-F10 -> 619292.47
A12: Inflation per year | C12: 0.025 | E12: Lost to inflation (nominal - real) | F12: =F4-F5 -> 478646.99
A13: Tax rate on gains | C13: 0 | E13: Check with Excel FV (no step-up, no tax) | F13: =IF(AND(C11=0,C13=0),FV(C15,C16,-C5,-C4,C7),"n/a (step-up or tax used)") -> n/a (step-up or tax used)
A14: Calculated
A15: Periodic rate i | C15: =IF(C9=C6,C8/C6,IF(C9<=0,EXP(C8/C6)-1,(1+C8/C9)^(C9/C6)-1)) -> 0.0058333333 | E15: Audit: live Excel vs Python engine | G15: Python | H15: Difference
A16: Number of periods N | C16: =ROUND(C10*C6,0) -> 360 | E16: Final value | F16: =F4 -> 914744.96 | G16: 914744.96 | H16: =ROUND(F16-G16,2) -> 0
A17: Effective annual return | C17: =IF(C9<=0,EXP(C8)-1,(1+C8/C9)^C9-1) -> 0.072290081 | E17: Total contributions | F17: =F7 -> 285452.49 | G17: 285452.49 | H17: =ROUND(F17-G17,2) -> 0
E18: Growth after tax | F18: =F11 -> 619292.47 | G18: 619292.47 | H18: =ROUND(F18-G18,2) -> 0
E19: Final value (real) | F19: =F5 -> 436097.97 | G19: 436097.97 | H19: =ROUND(F19-G19,2) -> 0
A21: i = (1 + R/m)^(m/p) - 1 is the rate per contribution period that earns the same effective annual return as R compounded m times a year (continuous: e^(R/p) - 1). Contribution in year y = C x (1 + step-up)^(y-1). Growth = (beginning balance + contribution if timing = 1) x i. Tax = growth x tax rate when growth > 0 (gains taxed as they accrue, no refund on losses). Real value = balance / (1 + inflation)^(period / p).
A24: Period | B24: Year | C24: Beginning balance | D24: Contribution | E24: Growth (before tax) | F24: Tax | G24: Ending balance | H24: Real value (today's money) | I24: Cumulative invested | J24: Cumulative growth after tax
A25: =1 -> 1 | B25: =INT((A25-1)/$C$6)+1 -> 1 | C25: =$C$4 -> 10000 | D25: =$C$5*(1+$C$11)^(B25-1) -> 500 | E25: =(C25+D25*$C$7)*$C$15 -> 58.333333 | F25: =IF(E25>0,E25*$C$13,0) -> 0 | G25: =C25+D25+E25-F25 -> 10558.333 | H25: =G25/(1+$C$12)^(A25/$C$6) -> 10536.63 | I25: =$C$4+D25 -> 10500 | J25: =E25-F25 -> 58.333333
A26: =A25+1 -> 2 | B26: =INT((A26-1)/$C$6)+1 -> 1 | C26: =G25 -> 10558.333 | D26: =$C$5*(1+$C$11)^(B26-1) -> 500 | E26: =(C26+D26*$C$7)*$C$15 -> 61.590278 | F26: =IF(E26>0,E26*$C$13,0) -> 0 | G26: =C26+D26+E26-F26 -> 11119.924 | H26: =G26/(1+$C$12)^(A26/$C$6) -> 11074.254 | I26: =I25+D26 -> 11000 | J26: =J25+E26-F26 -> 119.92361
A27: =A26+1 -> 3 | B27: =INT((A27-1)/$C$6)+1 -> 1 | C27: =G26 -> 11119.924 | D27: =$C$5*(1+$C$11)^(B27-1) -> 500 | E27: =(C27+D27*$C$7)*$C$15 -> 64.866221 | F27: =IF(E27>0,E27*$C$13,0) -> 0 | G27: =C27+D27+E27-F27 -> 11684.79 | H27: =G27/(1+$C$12)^(A27/$C$6) -> 11612.88 | I27: =I26+D27 -> 11500 | J27: =J26+E27-F27 -> 184.78983
A28: =A27+1 -> 4 | B28: =INT((A28-1)/$C$6)+1 -> 1 | C28: =G27 -> 11684.79 | D28: =$C$5*(1+$C$11)^(B28-1) -> 500 | E28: =(C28+D28*$C$7)*$C$15 -> 68.161274 | F28: =IF(E28>0,E28*$C$13,0) -> 0 | G28: =C28+D28+E28-F28 -> 12252.951 | H28: =G28/(1+$C$12)^(A28/$C$6) -> 12152.513 | I28: =I27+D28 -> 12000 | J28: =J27+E28-F28 -> 252.95111
A29: =A28+1 -> 5 | B29: =INT((A29-1)/$C$6)+1 -> 1 | C29: =G28 -> 12252.951 | D29: =$C$5*(1+$C$11)^(B29-1) -> 500 | E29: =(C29+D29*$C$7)*$C$15 -> 71.475548 | F29: =IF(E29>0,E29*$C$13,0) -> 0 | G29: =C29+D29+E29-F29 -> 12824.427 | H29: =G29/(1+$C$12)^(A29/$C$6) -> 12693.158 | I29: =I28+D29 -> 12500 | J29: =J28+E29-F29 -> 324.42665
A30: =A29+1 -> 6 | B30: =INT((A30-1)/$C$6)+1 -> 1 | C30: =G29 -> 12824.427 | D30: =$C$5*(1+$C$11)^(B30-1) -> 500 | E30: =(C30+D30*$C$7)*$C$15 -> 74.809155 | F30: =IF(E30>0,E30*$C$13,0) -> 0 | G30: =C30+D30+E30-F30 -> 13399.236 | H30: =G30/(1+$C$12)^(A30/$C$6) -> 13234.822 | I30: =I29+D30 -> 13000 | J30: =J29+E30-F30 -> 399.23581
A31: =A30+1 -> 7 | B31: =INT((A31-1)/$C$6)+1 -> 1 | C31: =G30 -> 13399.236 | D31: =$C$5*(1+$C$11)^(B31-1) -> 500 | E31: =(C31+D31*$C$7)*$C$15 -> 78.162209 | F31: =IF(E31>0,E31*$C$13,0) -> 0 | G31: =C31+D31+E31-F31 -> 13977.398 | H31: =G31/(1+$C$12)^(A31/$C$6) -> 13777.51 | I31: =I30+D31 -> 13500 | J31: =J30+E31-F31 -> 477.39802
A32: =A31+1 -> 8 | B32: =INT((A32-1)/$C$6)+1 -> 1 | C32: =G31 -> 13977.398 | D32: =$C$5*(1+$C$11)^(B32-1) -> 500 | E32: =(C32+D32*$C$7)*$C$15 -> 81.534822 | F32: =IF(E32>0,E32*$C$13,0) -> 0 | G32: =C32+D32+E32-F32 -> 14558.933 | H32: =G32/(1+$C$12)^(A32/$C$6) -> 14321.229 | I32: =I31+D32 -> 14000 | J32: =J31+E32-F32 -> 558.93284
A33: =A32+1 -> 9 | B33: =INT((A33-1)/$C$6)+1 -> 1 | C33: =G32 -> 14558.933 | D33: =$C$5*(1+$C$11)^(B33-1) -> 500 | E33: =(C33+D33*$C$7)*$C$15 -> 84.927108 | F33: =IF(E33>0,E33*$C$13,0) -> 0 | G33: =C33+D33+E33-F33 -> 15143.86 | H33: =G33/(1+$C$12)^(A33/$C$6) -> 14865.985 | I33: =I32+D33 -> 14500 | J33: =J32+E33-F33 -> 643.85995
A34: =A33+1 -> 10 | B34: =INT((A34-1)/$C$6)+1 -> 1 | C34: =G33 -> 15143.86 | D34: =$C$5*(1+$C$11)^(B34-1) -> 500 | E34: =(C34+D34*$C$7)*$C$15 -> 88.339183 | F34: =IF(E34>0,E34*$C$13,0) -> 0 | G34: =C34+D34+E34-F34 -> 15732.199 | H34: =G34/(1+$C$12)^(A34/$C$6) -> 15411.783 | I34: =I33+D34 -> 15000 | J34: =J33+E34-F34 -> 732.19913
A35: =A34+1 -> 11 | B35: =INT((A35-1)/$C$6)+1 -> 1 | C35: =G34 -> 15732.199 | D35: =$C$5*(1+$C$11)^(B35-1) -> 500 | E35: =(C35+D35*$C$7)*$C$15 -> 91.771162 | F35: =IF(E35>0,E35*$C$13,0) -> 0 | G35: =C35+D35+E35-F35 -> 16323.97 | H35: =G35/(1+$C$12)^(A35/$C$6) -> 15958.629 | I35: =I34+D35 -> 15500 | J35: =J34+E35-F35 -> 823.97029
A36: =A35+1 -> 12 | B36: =INT((A36-1)/$C$6)+1 -> 1 | C36: =G35 -> 16323.97 | D36: =$C$5*(1+$C$11)^(B36-1) -> 500 | E36: =(C36+D36*$C$7)*$C$15 -> 95.22316 | F36: =IF(E36>0,E36*$C$13,0) -> 0 | G36: =C36+D36+E36-F36 -> 16919.193 | H36: =G36/(1+$C$12)^(A36/$C$6) -> 16506.53 | I36: =I35+D36 -> 16000 | J36: =J35+E36-F36 -> 919.19345
A37: =A36+1 -> 13 | B37: =INT((A37-1)/$C$6)+1 -> 2 | C37: =G36 -> 16919.193 | D37: =$C$5*(1+$C$11)^(B37-1) -> 515 | E37: =(C37+D37*$C$7)*$C$15 -> 98.695295 | F37: =IF(E37>0,E37*$C$13,0) -> 0 | G37: =C37+D37+E37-F37 -> 17532.889 | H37: =G37/(1+$C$12)^(A37/$C$6) -> 17070.096 | I37: =I36+D37 -> 16515 | J37: =J36+E37-F37 -> 1017.8887
... A384: =A383+1 -> 360 | B384: =INT((A384-1)/$C$6)+1 -> 30 | C384: =G383 -> 908268.45 | D384: =$C$5*(1+$C$11)^(B384-1) -> 1178.2828 | E384: =(C384+D384*$C$7)*$C$15 -> 5298.2326 | F384: =IF(E384>0,E384*$C$13,0) -> 0 | G384: =C384+D384+E384-F384 -> 914744.96 | H384: =G384/(1+$C$12)^(A384/$C$6) -> 436097.97 | I384: =I383+D384 -> 295452.49 | J384: =J383+E384-F384 -> 619292.47

Sheet Investment (Annual)
A1: Investment Growth - Year by Year
A2: Each row sums the period rows of the 'Investment' sheet with SUMIF / INDEX formulas.
A4: Year | B4: Beginning balance | C4: Contributions | D4: Growth (before tax) | E4: Tax | F4: Ending balance | G4: Real value (today's money) | H4: Cumulative invested | I4: Cumulative growth after tax
A5: =1 -> 1 | B5: =INDEX(Investment!$C$25:$C$384,(A5-1)*Investment!$C$6+1) -> 10000 | C5: =SUMIF(Investment!$B$25:$B$384,A5,Investment!$D$25:$D$384) -> 6000 | D5: =SUMIF(Investment!$B$25:$B$384,A5,Investment!$E$25:$E$384) -> 919.19345 | E5: =SUMIF(Investment!$B$25:$B$384,A5,Investment!$F$25:$F$384) -> 0 | F5: =INDEX(Investment!$G$25:$G$384,MIN(1*Investment!$C$6,Investment!$C$16)) -> 16919.193 | G5: =INDEX(Investment!$H$25:$H$384,MIN(1*Investment!$C$6,Investment!$C$16)) -> 16506.53 | H5: =INDEX(Investment!$I$25:$I$384,MIN(1*Investment!$C$6,Investment!$C$16)) -> 16000 | I5: =INDEX(Investment!$J$25:$J$384,MIN(1*Investment!$C$6,Investment!$C$16)) -> 919.19345
A6: =A5+1 -> 2 | B6: =INDEX(Investment!$C$25:$C$384,(A6-1)*Investment!$C$6+1) -> 16919.193 | C6: =SUMIF(Investment!$B$25:$B$384,A6,Investment!$D$25:$D$384) -> 6180 | D6: =SUMIF(Investment!$B$25:$B$384,A6,Investment!$E$25:$E$384) -> 1425.2713 | E6: =SUMIF(Investment!$B$25:$B$384,A6,Investment!$F$25:$F$384) -> 0 | F6: =INDEX(Investment!$G$25:$G$384,MIN(2*Investment!$C$6,Investment!$C$16)) -> 24524.465 | G6: =INDEX(Investment!$H$25:$H$384,MIN(2*Investment!$C$6,Investment!$C$16)) -> 23342.739 | H6: =INDEX(Investment!$I$25:$I$384,MIN(2*Investment!$C$6,Investment!$C$16)) -> 22180 | I6: =INDEX(Investment!$J$25:$J$384,MIN(2*Investment!$C$6,Investment!$C$16)) -> 2344.4647
A7: =A6+1 -> 3 | B7: =INDEX(Investment!$C$25:$C$384,(A7-1)*Investment!$C$6+1) -> 24524.465 | C7: =SUMIF(Investment!$B$25:$B$384,A7,Investment!$D$25:$D$384) -> 6365.4 | D7: =SUMIF(Investment!$B$25:$B$384,A7,Investment!$E$25:$E$384) -> 1981.1224 | E7: =SUMIF(Investment!$B$25:$B$384,A7,Investment!$F$25:$F$384) -> 0 | F7: =INDEX(Investment!$G$25:$G$384,MIN(3*Investment!$C$6,Investment!$C$16)) -> 32870.987 | G7: =INDEX(Investment!$H$25:$H$384,MIN(3*Investment!$C$6,Investment!$C$16)) -> 30523.979 | H7: =INDEX(Investment!$I$25:$I$384,MIN(3*Investment!$C$6,Investment!$C$16)) -> 28545.4 | I7: =INDEX(Investment!$J$25:$J$384,MIN(3*Investment!$C$6,Investment!$C$16)) -> 4325.5871
A8: =A7+1 -> 4 | B8: =INDEX(Investment!$C$25:$C$384,(A8-1)*Investment!$C$6+1) -> 32870.987 | C8: =SUMIF(Investment!$B$25:$B$384,A8,Investment!$D$25:$D$384) -> 6556.362 | D8: =SUMIF(Investment!$B$25:$B$384,A8,Investment!$E$25:$E$384) -> 2590.7406 | E8: =SUMIF(Investment!$B$25:$B$384,A8,Investment!$F$25:$F$384) -> 0 | F8: =INDEX(Investment!$G$25:$G$384,MIN(4*Investment!$C$6,Investment!$C$16)) -> 42018.09 | G8: =INDEX(Investment!$H$25:$H$384,MIN(4*Investment!$C$6,Investment!$C$16)) -> 38066.315 | H8: =INDEX(Investment!$I$25:$I$384,MIN(4*Investment!$C$6,Investment!$C$16)) -> 35101.762 | I8: =INDEX(Investment!$J$25:$J$384,MIN(4*Investment!$C$6,Investment!$C$16)) -> 6916.3277
A9: =A8+1 -> 5 | B9: =INDEX(Investment!$C$25:$C$384,(A9-1)*Investment!$C$6+1) -> 42018.09 | C9: =SUMIF(Investment!$B$25:$B$384,A9,Investment!$D$25:$D$384) -> 6753.0529 | D9: =SUMIF(Investment!$B$25:$B$384,A9,Investment!$E$25:$E$384) -> 3258.4202 | E9: =SUMIF(Investment!$B$25:$B$384,A9,Investment!$F$25:$F$384) -> 0 | F9: =INDEX(Investment!$G$25:$G$384,MIN(5*Investment!$C$6,Investment!$C$16)) -> 52029.563 | G9: =INDEX(Investment!$H$25:$H$384,MIN(5*Investment!$C$6,Investment!$C$16)) -> 45986.552 | H9: =INDEX(Investment!$I$25:$I$384,MIN(5*Investment!$C$6,Investment!$C$16)) -> 41854.815 | I9: =INDEX(Investment!$J$25:$J$384,MIN(5*Investment!$C$6,Investment!$C$16)) -> 10174.748
A10: =A9+1 -> 6 | B10: =INDEX(Investment!$C$25:$C$384,(A10-1)*Investment!$C$6+1) -> 52029.563 | C10: =SUMIF(Investment!$B$25:$B$384,A10,Investment!$D$25:$D$384) -> 6955.6444 | D10: =SUMIF(Investment!$B$25:$B$384,A10,Investment!$E$25:$E$384) -> 3988.7783 | E10: =SUMIF(Investment!$B$25:$B$384,A10,Investment!$F$25:$F$384) -> 0 | F10: =INDEX(Investment!$G$25:$G$384,MIN(6*Investment!$C$6,Investment!$C$16)) -> 62973.986 | G10: =INDEX(Investment!$H$25:$H$384,MIN(6*Investment!$C$6,Investment!$C$16)) -> 54302.27 | H10: =INDEX(Investment!$I$25:$I$384,MIN(6*Investment!$C$6,Investment!$C$16)) -> 48810.459 | I10: =INDEX(Investment!$J$25:$J$384,MIN(6*Investment!$C$6,Investment!$C$16)) -> 14163.526
A11: =A10+1 -> 7 | B11: =INDEX(Investment!$C$25:$C$384,(A11-1)*Investment!$C$6+1) -> 62973.986 | C11: =SUMIF(Investment!$B$25:$B$384,A11,Investment!$D$25:$D$384) -> 7164.3138 | D11: =SUMIF(Investment!$B$25:$B$384,A11,Investment!$E$25:$E$384) -> 4786.7782 | E11: =SUMIF(Investment!$B$25:$B$384,A11,Investment!$F$25:$F$384) -> 0 | F11: =INDEX(Investment!$G$25:$G$384,MIN(7*Investment!$C$6,Investment!$C$16)) -> 74925.077 | G11: =INDEX(Investment!$H$25:$H$384,MIN(7*Investment!$C$6,Investment!$C$16)) -> 63031.863 | H11: =INDEX(Investment!$I$25:$I$384,MIN(7*Investment!$C$6,Investment!$C$16)) -> 55974.773 | I11: =INDEX(Investment!$J$25:$J$384,MIN(7*Investment!$C$6,Investment!$C$16)) -> 18950.304
A12: =A11+1 -> 8 | B12: =INDEX(Investment!$C$25:$C$384,(A12-1)*Investment!$C$6+1) -> 74925.077 | C12: =SUMIF(Investment!$B$25:$B$384,A12,Investment!$D$25:$D$384) -> 7379.2432 | D12: =SUMIF(Investment!$B$25:$B$384,A12,Investment!$E$25:$E$384) -> 5657.7551 | E12: =SUMIF(Investment!$B$25:$B$384,A12,Investment!$F$25:$F$384) -> 0 | F12: =INDEX(Investment!$G$25:$G$384,MIN(8*Investment!$C$6,Investment!$C$16)) -> 87962.076 | G12: =INDEX(Investment!$H$25:$H$384,MIN(8*Investment!$C$6,Investment!$C$16)) -> 72194.572 | H12: =INDEX(Investment!$I$25:$I$384,MIN(8*Investment!$C$6,Investment!$C$16)) -> 63354.016 | I12: =INDEX(Investment!$J$25:$J$384,MIN(8*Investment!$C$6,Investment!$C$16)) -> 24608.06
A13: =A12+1 -> 9 | B13: =INDEX(Investment!$C$25:$C$384,(A13-1)*Investment!$C$6+1) -> 87962.076 | C13: =SUMIF(Investment!$B$25:$B$384,A13,Investment!$D$25:$D$384) -> 7600.6205 | D13: =SUMIF(Investment!$B$25:$B$384,A13,Investment!$E$25:$E$384) -> 6607.4432 | E13: =SUMIF(Investment!$B$25:$B$384,A13,Investment!$F$25:$F$384) -> 0 | F13: =INDEX(Investment!$G$25:$G$384,MIN(9*Investment!$C$6,Investment!$C$16)) -> 102170.14 | G13: =INDEX(Investment!$H$25:$H$384,MIN(9*Investment!$C$6,Investment!$C$16)) -> 81810.528 | H13: =INDEX(Investment!$I$25:$I$384,MIN(9*Investment!$C$6,Investment!$C$16)) -> 70954.637 | I13: =INDEX(Investment!$J$25:$J$384,MIN(9*Investment!$C$6,Investment!$C$16)) -> 31215.503
A14: =A13+1 -> 10 | B14: =INDEX(Investment!$C$25:$C$384,(A14-1)*Investment!$C$6+1) -> 102170.14 | C14: =SUMIF(Investment!$B$25:$B$384,A14,Investment!$D$25:$D$384) -> 7828.6391 | D14: =SUMIF(Investment!$B$25:$B$384,A14,Investment!$E$25:$E$384) -> 7642.005 | E14: =SUMIF(Investment!$B$25:$B$384,A14,Investment!$F$25:$F$384) -> 0 | F14: =INDEX(Investment!$G$25:$G$384,MIN(10*Investment!$C$6,Investment!$C$16)) -> 117640.78 | G14: =INDEX(Investment!$H$25:$H$384,MIN(10*Investment!$C$6,Investment!$C$16)) -> 91900.792 | H14: =INDEX(Investment!$I$25:$I$384,MIN(10*Investment!$C$6,Investment!$C$16)) -> 78783.276 | I14: =INDEX(Investment!$J$25:$J$384,MIN(10*Investment!$C$6,Investment!$C$16)) -> 38857.508
A15: =A14+1 -> 11 | B15: =INDEX(Investment!$C$25:$C$384,(A15-1)*Investment!$C$6+1) -> 117640.78 | C15: =SUMIF(Investment!$B$25:$B$384,A15,Investment!$D$25:$D$384) -> 8063.4983 | D15: =SUMIF(Investment!$B$25:$B$384,A15,Investment!$E$25:$E$384) -> 8768.0627 | E15: =SUMIF(Investment!$B$25:$B$384,A15,Investment!$F$25:$F$384) -> 0 | F15: =INDEX(Investment!$G$25:$G$384,MIN(11*Investment!$C$6,Investment!$C$16)) -> 134472.34 | G15: =INDEX(Investment!$H$25:$H$384,MIN(11*Investment!$C$6,Investment!$C$16)) -> 102487.4 | H15: =INDEX(Investment!$I$25:$I$384,MIN(11*Investment!$C$6,Investment!$C$16)) -> 86846.774 | I15: =INDEX(Investment!$J$25:$J$384,MIN(11*Investment!$C$6,Investment!$C$16)) -> 47625.57
A16: =A15+1 -> 12 | B16: =INDEX(Investment!$C$25:$C$384,(A16-1)*Investment!$C$6+1) -> 134472.34 | C16: =SUMIF(Investment!$B$25:$B$384,A16,Investment!$D$25:$D$384) -> 8305.4032 | D16: =SUMIF(Investment!$B$25:$B$384,A16,Investment!$E$25:$E$384) -> 9992.7316 | E16: =SUMIF(Investment!$B$25:$B$384,A16,Investment!$F$25:$F$384) -> 0 | F16: =INDEX(Investment!$G$25:$G$384,MIN(12*Investment!$C$6,Investment!$C$16)) -> 152770.48 | G16: =INDEX(Investment!$H$25:$H$384,MIN(12*Investment!$C$6,Investment!$C$16)) -> 113593.39 | H16: =INDEX(Investment!$I$25:$I$384,MIN(12*Investment!$C$6,Investment!$C$16)) -> 95152.177 | I16: =INDEX(Investment!$J$25:$J$384,MIN(12*Investment!$C$6,Investment!$C$16)) -> 57618.302
A17: =A16+1 -> 13 | B17: =INDEX(Investment!$C$25:$C$384,(A17-1)*Investment!$C$6+1) -> 152770.48 | C17: =SUMIF(Investment!$B$25:$B$384,A17,Investment!$D$25:$D$384) -> 8554.5653 | D17: =SUMIF(Investment!$B$25:$B$384,A17,Investment!$E$25:$E$384) -> 11323.657 | E17: =SUMIF(Investment!$B$25:$B$384,A17,Investment!$F$25:$F$384) -> 0 | F17: =INDEX(Investment!$G$25:$G$384,MIN(13*Investment!$C$6,Investment!$C$16)) -> 172648.7 | G17: =INDEX(Investment!$H$25:$H$384,MIN(13*Investment!$C$6,Investment!$C$16)) -> 125242.89 | H17: =INDEX(Investment!$I$25:$I$384,MIN(13*Investment!$C$6,Investment!$C$16)) -> 103706.74 | I17: =INDEX(Investment!$J$25:$J$384,MIN(13*Investment!$C$6,Investment!$C$16)) -> 68941.959
A18: =A17+1 -> 14 | B18: =INDEX(Investment!$C$25:$C$384,(A18-1)*Investment!$C$6+1) -> 172648.7 | C18: =SUMIF(Investment!$B$25:$B$384,A18,Investment!$D$25:$D$384) -> 8811.2023 | D18: =SUMIF(Investment!$B$25:$B$384,A18,Investment!$E$25:$E$384) -> 12769.051 | E18: =SUMIF(Investment!$B$25:$B$384,A18,Investment!$F$25:$F$384) -> 0 | F18: =INDEX(Investment!$G$25:$G$384,MIN(14*Investment!$C$6,Investment!$C$16)) -> 194228.95 | G18: =INDEX(Investment!$H$25:$H$384,MIN(14*Investment!$C$6,Investment!$C$16)) -> 137461.11 | H18: =INDEX(Investment!$I$25:$I$384,MIN(14*Investment!$C$6,Investment!$C$16)) -> 112517.94 | I18: =INDEX(Investment!$J$25:$J$384,MIN(14*Investment!$C$6,Investment!$C$16)) -> 81711.01
A19: =A18+1 -> 15 | B19: =INDEX(Investment!$C$25:$C$384,(A19-1)*Investment!$C$6+1) -> 194228.95 | C19: =SUMIF(Investment!$B$25:$B$384,A19,Investment!$D$25:$D$384) -> 9075.5383 | D19: =SUMIF(Investment!$B$25:$B$384,A19,Investment!$E$25:$E$384) -> 14337.737 | E19: =SUMIF(Investment!$B$25:$B$384,A19,Investment!$F$25:$F$384) -> 0 | F19: =INDEX(Investment!$G$25:$G$384,MIN(15*Investment!$C$6,Investment!$C$16)) -> 217642.23 | G19: =INDEX(Investment!$H$25:$H$384,MIN(15*Investment!$C$6,Investment!$C$16)) -> 150274.46 | H19: =INDEX(Investment!$I$25:$I$384,MIN(15*Investment!$C$6,Investment!$C$16)) -> 121593.48 | I19: =INDEX(Investment!$J$25:$J$384,MIN(15*Investment!$C$6,Investment!$C$16)) -> 96048.747
A20: =A19+1 -> 16 | B20: =INDEX(Investment!$C$25:$C$384,(A20-1)*Investment!$C$6+1) -> 217642.23 | C20: =SUMIF(Investment!$B$25:$B$384,A20,Investment!$D$25:$D$384) -> 9347.8045 | D20: =SUMIF(Investment!$B$25:$B$384,A20,Investment!$E$25:$E$384) -> 16039.192 | E20: =SUMIF(Investment!$B$25:$B$384,A20,Investment!$F$25:$F$384) -> 0 | F20: =INDEX(Investment!$G$25:$G$384,MIN(16*Investment!$C$6,Investment!$C$16)) -> 243029.23 | G20: =INDEX(Investment!$H$25:$H$384,MIN(16*Investment!$C$6,Investment!$C$16)) -> 163710.55 | H20: =INDEX(Investment!$I$25:$I$384,MIN(16*Investment!$C$6,Investment!$C$16)) -> 130941.29 | I20: =INDEX(Investment!$J$25:$J$384,MIN(16*Investment!$C$6,Investment!$C$16)) -> 112087.94
A21: =A20+1 -> 17 | B21: =INDEX(Investment!$C$25:$C$384,(A21-1)*Investment!$C$6+1) -> 243029.23 | C21: =SUMIF(Investment!$B$25:$B$384,A21,Investment!$D$25:$D$384) -> 9628.2386 | D21: =SUMIF(Investment!$B$25:$B$384,A21,Investment!$E$25:$E$384) -> 17883.595 | E21: =SUMIF(Investment!$B$25:$B$384,A21,Investment!$F$25:$F$384) -> 0 | F21: =INDEX(Investment!$G$25:$G$384,MIN(17*Investment!$C$6,Investment!$C$16)) -> 270541.06 | G21: =INDEX(Investment!$H$25:$H$384,MIN(17*Investment!$C$6,Investment!$C$16)) -> 177798.25 | H21: =INDEX(Investment!$I$25:$I$384,MIN(17*Investment!$C$6,Investment!$C$16)) -> 140569.53 | I21: =INDEX(Investment!$J$25:$J$384,MIN(17*Investment!$C$6,Investment!$C$16)) -> 129971.53
A22: =A21+1 -> 18 | B22: =INDEX(Investment!$C$25:$C$384,(A22-1)*Investment!$C$6+1) -> 270541.06 | C22: =SUMIF(Investment!$B$25:$B$384,A22,Investment!$D$25:$D$384) -> 9917.0858 | D22: =SUMIF(Investment!$B$25:$B$384,A22,Investment!$E$25:$E$384) -> 19881.877 | E22: =SUMIF(Investment!$B$25:$B$384,A22,Investment!$F$25:$F$384) -> 0 | F22: =INDEX(Investment!$G$25:$G$384,MIN(18*Investment!$C$6,Investment!$C$16)) -> 300340.02 | G22: =INDEX(Investment!$H$25:$H$384,MIN(18*Investment!$C$6,Investment!$C$16)) -> 192567.78 | H22: =INDEX(Investment!$I$25:$I$384,MIN(18*Investment!$C$6,Investment!$C$16)) -> 150486.61 | I22: =INDEX(Investment!$J$25:$J$384,MIN(18*Investment!$C$6,Investment!$C$16)) -> 149853.41
A23: =A22+1 -> 19 | B23: =INDEX(Investment!$C$25:$C$384,(A23-1)*Investment!$C$6+1) -> 300340.02 | C23: =SUMIF(Investment!$B$25:$B$384,A23,Investment!$D$25:$D$384) -> 10214.598 | D23: =SUMIF(Investment!$B$25:$B$384,A23,Investment!$E$25:$E$384) -> 22045.78 | E23: =SUMIF(Investment!$B$25:$B$384,A23,Investment!$F$25:$F$384) -> 0 | F23: =INDEX(Investment!$G$25:$G$384,MIN(19*Investment!$C$6,Investment!$C$16)) -> 332600.4 | G23: =INDEX(Investment!$H$25:$H$384,MIN(19*Investment!$C$6,Investment!$C$16)) -> 208050.77 | H23: =INDEX(Investment!$I$25:$I$384,MIN(19*Investment!$C$6,Investment!$C$16)) -> 160701.21 | I23: =INDEX(Investment!$J$25:$J$384,MIN(19*Investment!$C$6,Investment!$C$16)) -> 171899.19
A24: =A23+1 -> 20 | B24: =INDEX(Investment!$C$25:$C$384,(A24-1)*Investment!$C$6+1) -> 332600.4 | C24: =SUMIF(Investment!$B$25:$B$384,A24,Investment!$D$25:$D$384) -> 10521.036 | D24: =SUMIF(Investment!$B$25:$B$384,A24,Investment!$E$25:$E$384) -> 24387.91 | E24: =SUMIF(Investment!$B$25:$B$384,A24,Investment!$F$25:$F$384) -> 0 | F24: =INDEX(Investment!$G$25:$G$384,MIN(20*Investment!$C$6,Investment!$C$16)) -> 367509.35 | G24: =INDEX(Investment!$H$25:$H$384,MIN(20*Investment!$C$6,Investment!$C$16)) -> 224280.28 | H24: =INDEX(Investment!$I$25:$I$384,MIN(20*Investment!$C$6,Investment!$C$16)) -> 171222.25 | I24: =INDEX(Investment!$J$25:$J$384,MIN(20*Investment!$C$6,Investment!$C$16)) -> 196287.1
A25: =A24+1 -> 21 | B25: =INDEX(Investment!$C$25:$C$384,(A25-1)*Investment!$C$6+1) -> 367509.35 | C25: =SUMIF(Investment!$B$25:$B$384,A25,Investment!$D$25:$D$384) -> 10836.667 | D25: =SUMIF(Investment!$B$25:$B$384,A25,Investment!$E$25:$E$384) -> 26921.807 | E25: =SUMIF(Investment!$B$25:$B$384,A25,Investment!$F$25:$F$384) -> 0 | F25: =INDEX(Investment!$G$25:$G$384,MIN(21*Investment!$C$6,Investment!$C$16)) -> 405267.82 | G25: =INDEX(Investment!$H$25:$H$384,MIN(21*Investment!$C$6,Investment!$C$16)) -> 241290.9 | H25: =INDEX(Investment!$I$25:$I$384,MIN(21*Investment!$C$6,Investment!$C$16)) -> 182058.91 | I25: =INDEX(Investment!$J$25:$J$384,MIN(21*Investment!$C$6,Investment!$C$16)) -> 223208.91
A26: =A25+1 -> 22 | B26: =INDEX(Investment!$C$25:$C$384,(A26-1)*Investment!$C$6+1) -> 405267.82 | C26: =SUMIF(Investment!$B$25:$B$384,A26,Investment!$D$25:$D$384) -> 11161.767 | D26: =SUMIF(Investment!$B$25:$B$384,A26,Investment!$E$25:$E$384) -> 29662.006 | E26: =SUMIF(Investment!$B$25:$B$384,A26,Investment!$F$25:$F$384) -> 0 | F26: =INDEX(Investment!$G$25:$G$384,MIN(22*Investment!$C$6,Investment!$C$16)) -> 446091.59 | G26: =INDEX(Investment!$H$25:$H$384,MIN(22*Investment!$C$6,Investment!$C$16)) -> 259118.85 | H26: =INDEX(Investment!$I$25:$I$384,MIN(22*Investment!$C$6,Investment!$C$16)) -> 193220.68 | I26: =INDEX(Investment!$J$25:$J$384,MIN(22*Investment!$C$6,Investment!$C$16)) -> 252870.91
A27: =A26+1 -> 23 | B27: =INDEX(Investment!$C$25:$C$384,(A27-1)*Investment!$C$6+1) -> 446091.59 | C27: =SUMIF(Investment!$B$25:$B$384,A27,Investment!$D$25:$D$384) -> 11496.62 | D27: =SUMIF(Investment!$B$25:$B$384,A27,Investment!$E$25:$E$384) -> 32624.114 | E27: =SUMIF(Investment!$B$25:$B$384,A27,Investment!$F$25:$F$384) -> 0 | F27: =INDEX(Investment!$G$25:$G$384,MIN(23*Investment!$C$6,Investment!$C$16)) -> 490212.33 | G27: =INDEX(Investment!$H$25:$H$384,MIN(23*Investment!$C$6,Investment!$C$16)) -> 277801.97 | H27: =INDEX(Investment!$I$25:$I$384,MIN(23*Investment!$C$6,Investment!$C$16)) -> 204717.3 | I27: =INDEX(Investment!$J$25:$J$384,MIN(23*Investment!$C$6,Investment!$C$16)) -> 285495.03
A28: =A27+1 -> 24 | B28: =INDEX(Investment!$C$25:$C$384,(A28-1)*Investment!$C$6+1) -> 490212.33 | C28: =SUMIF(Investment!$B$25:$B$384,A28,Investment!$D$25:$D$384) -> 11841.519 | D28: =SUMIF(Investment!$B$25:$B$384,A28,Investment!$E$25:$E$384) -> 35824.889 | E28: =SUMIF(Investment!$B$25:$B$384,A28,Investment!$F$25:$F$384) -> 0 | F28: =INDEX(Investment!$G$25:$G$384,MIN(24*Investment!$C$6,Investment!$C$16)) -> 537878.74 | G28: =INDEX(Investment!$H$25:$H$384,MIN(24*Investment!$C$6,Investment!$C$16)) -> 297379.9 | H28: =INDEX(Investment!$I$25:$I$384,MIN(24*Investment!$C$6,Investment!$C$16)) -> 216558.82 | I28: =INDEX(Investment!$J$25:$J$384,MIN(24*Investment!$C$6,Investment!$C$16)) -> 321319.92
A29: =A28+1 -> 25 | B29: =INDEX(Investment!$C$25:$C$384,(A29-1)*Investment!$C$6+1) -> 537878.74 | C29: =SUMIF(Investment!$B$25:$B$384,A29,Investment!$D$25:$D$384) -> 12196.765 | D29: =SUMIF(Investment!$B$25:$B$384,A29,Investment!$E$25:$E$384) -> 39282.32 | E29: =SUMIF(Investment!$B$25:$B$384,A29,Investment!$F$25:$F$384) -> 0 | F29: =INDEX(Investment!$G$25:$G$384,MIN(25*Investment!$C$6,Investment!$C$16)) -> 589357.82 | G29: =INDEX(Investment!$H$25:$H$384,MIN(25*Investment!$C$6,Investment!$C$16)) -> 317894.06 | H29: =INDEX(Investment!$I$25:$I$384,MIN(25*Investment!$C$6,Investment!$C$16)) -> 228755.59 | I29: =INDEX(Investment!$J$25:$J$384,MIN(25*Investment!$C$6,Investment!$C$16)) -> 360602.24
A30: =A29+1 -> 26 | B30: =INDEX(Investment!$C$25:$C$384,(A30-1)*Investment!$C$6+1) -> 589357.82 | C30: =SUMIF(Investment!$B$25:$B$384,A30,Investment!$D$25:$D$384) -> 12562.668 | D30: =SUMIF(Investment!$B$25:$B$384,A30,Investment!$E$25:$E$384) -> 43015.718 | E30: =SUMIF(Investment!$B$25:$B$384,A30,Investment!$F$25:$F$384) -> 0 | F30: =INDEX(Investment!$G$25:$G$384,MIN(26*Investment!$C$6,Investment!$C$16)) -> 644936.21 | G30: =INDEX(Investment!$H$25:$H$384,MIN(26*Investment!$C$6,Investment!$C$16)) -> 339387.83 | H30: =INDEX(Investment!$I$25:$I$384,MIN(26*Investment!$C$6,Investment!$C$16)) -> 241318.25 | I30: =INDEX(Investment!$J$25:$J$384,MIN(26*Investment!$C$6,Investment!$C$16)) -> 403617.95
A31: =A30+1 -> 27 | B31: =INDEX(Investment!$C$25:$C$384,(A31-1)*Investment!$C$6+1) -> 644936.21 | C31: =SUMIF(Investment!$B$25:$B$384,A31,Investment!$D$25:$D$384) -> 12939.548 | D31: =SUMIF(Investment!$B$25:$B$384,A31,Investment!$E$25:$E$384) -> 47045.814 | E31: =SUMIF(Investment!$B$25:$B$384,A31,Investment!$F$25:$F$384) -> 0 | F31: =INDEX(Investment!$G$25:$G$384,MIN(27*Investment!$C$6,Investment!$C$16)) -> 704921.57 | G31: =INDEX(Investment!$H$25:$H$384,MIN(27*Investment!$C$6,Investment!$C$16)) -> 361906.54 | H31: =INDEX(Investment!$I$25:$I$384,MIN(27*Investment!$C$6,Investment!$C$16)) -> 254257.8 | I31: =INDEX(Investment!$J$25:$J$384,MIN(27*Investment!$C$6,Investment!$C$16)) -> 450663.77
A32: =A31+1 -> 28 | B32: =INDEX(Investment!$C$25:$C$384,(A32-1)*Investment!$C$6+1) -> 704921.57 | C32: =SUMIF(Investment!$B$25:$B$384,A32,Investment!$D$25:$D$384) -> 13327.734 | D32: =SUMIF(Investment!$B$25:$B$384,A32,Investment!$E$25:$E$384) -> 51394.86 | E32: =SUMIF(Investment!$B$25:$B$384,A32,Investment!$F$25:$F$384) -> 0 | F32: =INDEX(Investment!$G$25:$G$384,MIN(28*Investment!$C$6,Investment!$C$16)) -> 769644.16 | G32: =INDEX(Investment!$H$25:$H$384,MIN(28*Investment!$C$6,Investment!$C$16)) -> 385497.66 | H32: =INDEX(Investment!$I$25:$I$384,MIN(28*Investment!$C$6,Investment!$C$16)) -> 267585.54 | I32: =INDEX(Investment!$J$25:$J$384,MIN(28*Investment!$C$6,Investment!$C$16)) -> 502058.63
A33: =A32+1 -> 29 | B33: =INDEX(Investment!$C$25:$C$384,(A33-1)*Investment!$C$6+1) -> 769644.16 | C33: =SUMIF(Investment!$B$25:$B$384,A33,Investment!$D$25:$D$384) -> 13727.566 | D33: =SUMIF(Investment!$B$25:$B$384,A33,Investment!$E$25:$E$384) -> 56086.742 | E33: =SUMIF(Investment!$B$25:$B$384,A33,Investment!$F$25:$F$384) -> 0 | F33: =INDEX(Investment!$G$25:$G$384,MIN(29*Investment!$C$6,Investment!$C$16)) -> 839458.47 | G33: =INDEX(Investment!$H$25:$H$384,MIN(29*Investment!$C$6,Investment!$C$16)) -> 410210.83 | H33: =INDEX(Investment!$I$25:$I$384,MIN(29*Investment!$C$6,Investment!$C$16)) -> 281313.1 | I33: =INDEX(Investment!$J$25:$J$384,MIN(29*Investment!$C$6,Investment!$C$16)) -> 558145.37
A34: =A33+1 -> 30 | B34: =INDEX(Investment!$C$25:$C$384,(A34-1)*Investment!$C$6+1) -> 839458.47 | C34: =SUMIF(Investment!$B$25:$B$384,A34,Investment!$D$25:$D$384) -> 14139.393 | D34: =SUMIF(Investment!$B$25:$B$384,A34,Investment!$E$25:$E$384) -> 61147.097 | E34: =SUMIF(Investment!$B$25:$B$384,A34,Investment!$F$25:$F$384) -> 0 | F34: =INDEX(Investment!$G$25:$G$384,MIN(30*Investment!$C$6,Investment!$C$16)) -> 914744.96 | G34: =INDEX(Investment!$H$25:$H$384,MIN(30*Investment!$C$6,Investment!$C$16)) -> 436097.97 | H34: =INDEX(Investment!$I$25:$I$384,MIN(30*Investment!$C$6,Investment!$C$16)) -> 295452.49 | I34: =INDEX(Investment!$J$25:$J$384,MIN(30*Investment!$C$6,Investment!$C$16)) -> 619292.47

Sheet TVM Functions
A1: Excel TVM Functions - worked examples
A2: Excel signs: money you receive is +, money you pay is -. Rates and periods must use the same unit.
A4: Function | B4: Result | C4: What it shows
A5: Investment (uses the Investment sheet inputs)
A6: FV(i, N, -C, -initial, timing) | B6: =FV(Investment!C15,Investment!C16,-Investment!C5,-Investment!C4,Investment!C7) -> 691150.47 | C6: Final value if there were no step-up and no tax
A7: PV of the final value at the inflation rate | B7: =Investment!F4/(1+Investment!C12)^Investment!C10 -> 436097.97 | C7: Same as the real final value
A8: Rates
A9: EFFECT(6%, 12) | B9: =EFFECT(0.06,12) -> 0.061677812 | C9: 6% APR compounded monthly = 6.168% EAR
A10: NOMINAL(6.168%, 12) | B10: =NOMINAL(EFFECT(0.06,12),12) -> 0.06 | C10: Back to 6.000% APR
A11: Project: -100,000 at t=0, then 25k, 35k, 40k, 35k, 30k; rate 10%
A12: Correct NPV = CF0 + NPV(10%, CF1..CF5) | B12: =-100000+NPV(0.1,25000,35000,40000,35000,30000) -> 24238.595 | C12: Excel NPV discounts its FIRST value by one period, so CF0 stays outside
A13: Common mistake: NPV(10%, CF0..CF5) | B13: =NPV(0.1,-100000,25000,35000,40000,35000,30000) -> 22035.087 | C13: Discounts everything one period too much (= correct NPV / 1.10)
A14: IRR({CF0..CF5}) | B14: =IRR({-100000,25000,35000,40000,35000,30000}) -> 0.18777806 | C14: IRR treats the first value as t = 0
