Workbook

Sheet Loan
A1: Loan Amortization Model
A2: Yellow cells with blue numbers are inputs. Every other number is a live formula. Rows were created for the contractual term; shortening the term works, lengthening it needs a new export.
A3: Inputs | E3: Lump-sum extra payments | H3: Summary (live)
A4: Loan amount | C4: 300000 | E4: Payment # | F4: Amount | H4: Payments actually made | I4: =COUNTIF($C$32:$C$331,">0") -> 233
A5: Annual rate (nominal APR) | C5: 0.06 | E5: 60 | F5: 10000 | H5: Payoff date | I5: =INDEX($B$32:$B$331,I4) -> 53387
A6: Term (years) | C6: 25 | H6: Original payoff date (no extras) | I6: =INDEX($B$32:$B$331,MIN(C17,ROWS($B$32:$B$331))) -> 55427
A7: Payments per year p | C7: 12 | H7: Total interest | I7: =SUM($D$32:$D$331) -> 205217.43
A8: Compounding per year m | C8: 12 | H8: Total extra principal | I8: =SUM($G$32:$G$331) -> 56400
A9: First payment date | C9: 46327 | H9: Total of all payments | I9: =SUM($H$32:$H$331) -> 505217.43
A10: Loan type (1, 2 or 3) | C10: 1 | H10: Final payment (incl. balloon) | I10: =INDEX($H$32:$H$331,I4) -> 384.63
A11: Balloon (type 1 only) | C11: 0 | H11: Interest without extras | I11: =SUM($N$32:$N$331) -> 279872.8
A12: Extra per payment | C12: 200 | H12: Interest saved by extras | I12: =I11-I7 -> 74655.37
A13: Extra from payment # | C13: 1 | H13: Payments saved | I13: =C17-I4 -> 67
H14: Years saved | I14: =I13/C7 -> 5.5833333
A15: Calculated terms
A16: Periodic rate i | C16: =IF(C8=C7,C5/C7,IF(C8<=0,EXP(C5/C7)-1,(1+C5/C8)^(C8/C7)-1)) -> 0.005 | H16: Audit: live Excel vs Python engine
A17: Number of payments N | C17: =ROUND(C6*C7,0) -> 300 | H17: Item | I17: Excel (live) | J17: Python | K17: Difference
A18: Regular payment | C18: =IF(C10=1,ROUND(IF(C16=0,(C4-C11)/C17,-PMT(C16,C17,C4,-C11)),2),IF(C10=2,ROUND(C4/C17,2)+ROUND(C4*C16,2),ROUND(C4*C16,2))) -> 1932.9 | H18: Regular payment | I18: =C18 -> 1932.9 | J18: 1932.9 | K18: =ROUND(I18-J18,2) -> 0
A19: Principal / payment (type 2) | C19: =ROUND(C4/C17,2) -> 1000 | H19: Total interest | I19: =I7 -> 205217.43 | J19: 205217.43 | K19: =ROUND(I19-J19,2) -> 0
A20: Effective annual rate | C20: =IF(C8<=0,EXP(C5)-1,(1+C5/C8)^C8-1) -> 0.061677812 | H20: Total of all payments | I20: =I9 -> 505217.43 | J20: 505217.43 | K20: =ROUND(I20-J20,2) -> 0
H21: Payments made | I21: =I4 -> 233 | J21: 233 | K21: =ROUND(I21-J21,2) -> 0
A22: Loan type: 1 = fixed payment (annuity, =PMT), 2 = equal principal, 3 = interest-only with the whole principal as a balloon. Periodic rate i = (1 + APR/m)^(m/p) - 1, which is simply APR/p when m = p (the usual case). Rules: interest = ROUND(balance x i, 2). Scheduled payment = MIN(regular payment, balance + interest); the last contractual payment pays off the whole balance (this is where a balloon is paid). Extra payments go to principal, capped at the remaining balance; the regular payment is not recalculated, so the loan ends earlier. Dates: monthly-type frequencies use EDATE from the first payment date (31 Jan -> 28/29 Feb -> 31 Mar); bi-weekly/weekly add 14/7 days. | H22: Interest saved | I22: =I12 -> 74655.37 | J22: 74655.37 | K22: =ROUND(I22-J22,2) -> 0
H24: Python values are frozen at export time; differences stay 0.00 until you change an input.
M30: Baseline = same loan without any extra payments (for 'interest saved')
A31: Payment # | B31: Date | C31: Beginning balance | D31: Interest | E31: Scheduled payment | F31: Scheduled principal | G31: Extra principal | H31: Total payment | I31: Ending balance | J31: Cumulative interest | K31: Cumulative principal | M31: Baseline: beginning | N31: Baseline: interest | O31: Baseline: payment | P31: Baseline: principal | Q31: Baseline: ending
A32: =1 -> 1 | B32: =IF(MOD(12,$C$7)=0,EDATE($C$9,(A32-1)*12/$C$7),$C$9+(A32-1)*ROUND(364/$C$7,0)) -> 46327 | C32: =ROUND($C$4,2) -> 300000 | D32: =ROUND(C32*$C$16,2) -> 1500 | E32: =IF(C32<=0,0,ROUND(CHOOSE($C$10,IF(A32=$C$17,C32+D32,MIN($C$18,C32+D32)),IF(A32=$C$17,C32,MIN($C$19,C32))+D32,IF(A32=$C$17,C32,0)+D32),2)) -> 1932.9 | F32: =IF(C32<=0,0,MAX(0,ROUND(E32-D32,2))) -> 432.9 | G32: =IF(C32<=0,0,ROUND(MIN(MAX(0,C32-F32),MAX(0,IF(A32>=$C$13,$C$12,0)+SUMIF($E$5:$E$14,A32,$F$5:$F$14))),2)) -> 200 | H32: =ROUND(E32+G32,2) -> 2132.9 | I32: =ROUND(C32-F32-G32,2) -> 299367.1 | J32: =ROUND(D32,2) -> 1500 | K32: =ROUND(F32+G32,2) -> 632.9 | M32: =ROUND($C$4,2) -> 300000 | N32: =ROUND(M32*$C$16,2) -> 1500 | O32: =IF(M32<=0,0,ROUND(CHOOSE($C$10,IF(A32=$C$17,M32+N32,MIN($C$18,M32+N32)),IF(A32=$C$17,M32,MIN($C$19,M32))+N32,IF(A32=$C$17,M32,0)+N32),2)) -> 1932.9 | P32: =IF(M32<=0,0,MAX(0,ROUND(O32-N32,2))) -> 432.9 | Q32: =ROUND(M32-P32,2) -> 299567.1
A33: =A32+1 -> 2 | B33: =IF(MOD(12,$C$7)=0,EDATE($C$9,(A33-1)*12/$C$7),$C$9+(A33-1)*ROUND(364/$C$7,0)) -> 46357 | C33: =I32 -> 299367.1 | D33: =ROUND(C33*$C$16,2) -> 1496.84 | E33: =IF(C33<=0,0,ROUND(CHOOSE($C$10,IF(A33=$C$17,C33+D33,MIN($C$18,C33+D33)),IF(A33=$C$17,C33,MIN($C$19,C33))+D33,IF(A33=$C$17,C33,0)+D33),2)) -> 1932.9 | F33: =IF(C33<=0,0,MAX(0,ROUND(E33-D33,2))) -> 436.06 | G33: =IF(C33<=0,0,ROUND(MIN(MAX(0,C33-F33),MAX(0,IF(A33>=$C$13,$C$12,0)+SUMIF($E$5:$E$14,A33,$F$5:$F$14))),2)) -> 200 | H33: =ROUND(E33+G33,2) -> 2132.9 | I33: =ROUND(C33-F33-G33,2) -> 298731.04 | J33: =ROUND(J32+D33,2) -> 2996.84 | K33: =ROUND(K32+F33+G33,2) -> 1268.96 | M33: =Q32 -> 299567.1 | N33: =ROUND(M33*$C$16,2) -> 1497.84 | O33: =IF(M33<=0,0,ROUND(CHOOSE($C$10,IF(A33=$C$17,M33+N33,MIN($C$18,M33+N33)),IF(A33=$C$17,M33,MIN($C$19,M33))+N33,IF(A33=$C$17,M33,0)+N33),2)) -> 1932.9 | P33: =IF(M33<=0,0,MAX(0,ROUND(O33-N33,2))) -> 435.06 | Q33: =ROUND(M33-P33,2) -> 299132.04
A34: =A33+1 -> 3 | B34: =IF(MOD(12,$C$7)=0,EDATE($C$9,(A34-1)*12/$C$7),$C$9+(A34-1)*ROUND(364/$C$7,0)) -> 46388 | C34: =I33 -> 298731.04 | D34: =ROUND(C34*$C$16,2) -> 1493.66 | E34: =IF(C34<=0,0,ROUND(CHOOSE($C$10,IF(A34=$C$17,C34+D34,MIN($C$18,C34+D34)),IF(A34=$C$17,C34,MIN($C$19,C34))+D34,IF(A34=$C$17,C34,0)+D34),2)) -> 1932.9 | F34: =IF(C34<=0,0,MAX(0,ROUND(E34-D34,2))) -> 439.24 | G34: =IF(C34<=0,0,ROUND(MIN(MAX(0,C34-F34),MAX(0,IF(A34>=$C$13,$C$12,0)+SUMIF($E$5:$E$14,A34,$F$5:$F$14))),2)) -> 200 | H34: =ROUND(E34+G34,2) -> 2132.9 | I34: =ROUND(C34-F34-G34,2) -> 298091.8 | J34: =ROUND(J33+D34,2) -> 4490.5 | K34: =ROUND(K33+F34+G34,2) -> 1908.2 | M34: =Q33 -> 299132.04 | N34: =ROUND(M34*$C$16,2) -> 1495.66 | O34: =IF(M34<=0,0,ROUND(CHOOSE($C$10,IF(A34=$C$17,M34+N34,MIN($C$18,M34+N34)),IF(A34=$C$17,M34,MIN($C$19,M34))+N34,IF(A34=$C$17,M34,0)+N34),2)) -> 1932.9 | P34: =IF(M34<=0,0,MAX(0,ROUND(O34-N34,2))) -> 437.24 | Q34: =ROUND(M34-P34,2) -> 298694.8
A35: =A34+1 -> 4 | B35: =IF(MOD(12,$C$7)=0,EDATE($C$9,(A35-1)*12/$C$7),$C$9+(A35-1)*ROUND(364/$C$7,0)) -> 46419 | C35: =I34 -> 298091.8 | D35: =ROUND(C35*$C$16,2) -> 1490.46 | E35: =IF(C35<=0,0,ROUND(CHOOSE($C$10,IF(A35=$C$17,C35+D35,MIN($C$18,C35+D35)),IF(A35=$C$17,C35,MIN($C$19,C35))+D35,IF(A35=$C$17,C35,0)+D35),2)) -> 1932.9 | F35: =IF(C35<=0,0,MAX(0,ROUND(E35-D35,2))) -> 442.44 | G35: =IF(C35<=0,0,ROUND(MIN(MAX(0,C35-F35),MAX(0,IF(A35>=$C$13,$C$12,0)+SUMIF($E$5:$E$14,A35,$F$5:$F$14))),2)) -> 200 | H35: =ROUND(E35+G35,2) -> 2132.9 | I35: =ROUND(C35-F35-G35,2) -> 297449.36 | J35: =ROUND(J34+D35,2) -> 5980.96 | K35: =ROUND(K34+F35+G35,2) -> 2550.64 | M35: =Q34 -> 298694.8 | N35: =ROUND(M35*$C$16,2) -> 1493.47 | O35: =IF(M35<=0,0,ROUND(CHOOSE($C$10,IF(A35=$C$17,M35+N35,MIN($C$18,M35+N35)),IF(A35=$C$17,M35,MIN($C$19,M35))+N35,IF(A35=$C$17,M35,0)+N35),2)) -> 1932.9 | P35: =IF(M35<=0,0,MAX(0,ROUND(O35-N35,2))) -> 439.43 | Q35: =ROUND(M35-P35,2) -> 298255.37
A36: =A35+1 -> 5 | B36: =IF(MOD(12,$C$7)=0,EDATE($C$9,(A36-1)*12/$C$7),$C$9+(A36-1)*ROUND(364/$C$7,0)) -> 46447 | C36: =I35 -> 297449.36 | D36: =ROUND(C36*$C$16,2) -> 1487.25 | E36: =IF(C36<=0,0,ROUND(CHOOSE($C$10,IF(A36=$C$17,C36+D36,MIN($C$18,C36+D36)),IF(A36=$C$17,C36,MIN($C$19,C36))+D36,IF(A36=$C$17,C36,0)+D36),2)) -> 1932.9 | F36: =IF(C36<=0,0,MAX(0,ROUND(E36-D36,2))) -> 445.65 | G36: =IF(C36<=0,0,ROUND(MIN(MAX(0,C36-F36),MAX(0,IF(A36>=$C$13,$C$12,0)+SUMIF($E$5:$E$14,A36,$F$5:$F$14))),2)) -> 200 | H36: =ROUND(E36+G36,2) -> 2132.9 | I36: =ROUND(C36-F36-G36,2) -> 296803.71 | J36: =ROUND(J35+D36,2) -> 7468.21 | K36: =ROUND(K35+F36+G36,2) -> 3196.29 | M36: =Q35 -> 298255.37 | N36: =ROUND(M36*$C$16,2) -> 1491.28 | O36: =IF(M36<=0,0,ROUND(CHOOSE($C$10,IF(A36=$C$17,M36+N36,MIN($C$18,M36+N36)),IF(A36=$C$17,M36,MIN($C$19,M36))+N36,IF(A36=$C$17,M36,0)+N36),2)) -> 1932.9 | P36: =IF(M36<=0,0,MAX(0,ROUND(O36-N36,2))) -> 441.62 | Q36: =ROUND(M36-P36,2) -> 297813.75
A37: =A36+1 -> 6 | B37: =IF(MOD(12,$C$7)=0,EDATE($C$9,(A37-1)*12/$C$7),$C$9+(A37-1)*ROUND(364/$C$7,0)) -> 46478 | C37: =I36 -> 296803.71 | D37: =ROUND(C37*$C$16,2) -> 1484.02 | E37: =IF(C37<=0,0,ROUND(CHOOSE($C$10,IF(A37=$C$17,C37+D37,MIN($C$18,C37+D37)),IF(A37=$C$17,C37,MIN($C$19,C37))+D37,IF(A37=$C$17,C37,0)+D37),2)) -> 1932.9 | F37: =IF(C37<=0,0,MAX(0,ROUND(E37-D37,2))) -> 448.88 | G37: =IF(C37<=0,0,ROUND(MIN(MAX(0,C37-F37),MAX(0,IF(A37>=$C$13,$C$12,0)+SUMIF($E$5:$E$14,A37,$F$5:$F$14))),2)) -> 200 | H37: =ROUND(E37+G37,2) -> 2132.9 | I37: =ROUND(C37-F37-G37,2) -> 296154.83 | J37: =ROUND(J36+D37,2) -> 8952.23 | K37: =ROUND(K36+F37+G37,2) -> 3845.17 | M37: =Q36 -> 297813.75 | N37: =ROUND(M37*$C$16,2) -> 1489.07 | O37: =IF(M37<=0,0,ROUND(CHOOSE($C$10,IF(A37=$C$17,M37+N37,MIN($C$18,M37+N37)),IF(A37=$C$17,M37,MIN($C$19,M37))+N37,IF(A37=$C$17,M37,0)+N37),2)) -> 1932.9 | P37: =IF(M37<=0,0,MAX(0,ROUND(O37-N37,2))) -> 443.83 | Q37: =ROUND(M37-P37,2) -> 297369.92
A38: =A37+1 -> 7 | B38: =IF(MOD(12,$C$7)=0,EDATE($C$9,(A38-1)*12/$C$7),$C$9+(A38-1)*ROUND(364/$C$7,0)) -> 46508 | C38: =I37 -> 296154.83 | D38: =ROUND(C38*$C$16,2) -> 1480.77 | E38: =IF(C38<=0,0,ROUND(CHOOSE($C$10,IF(A38=$C$17,C38+D38,MIN($C$18,C38+D38)),IF(A38=$C$17,C38,MIN($C$19,C38))+D38,IF(A38=$C$17,C38,0)+D38),2)) -> 1932.9 | F38: =IF(C38<=0,0,MAX(0,ROUND(E38-D38,2))) -> 452.13 | G38: =IF(C38<=0,0,ROUND(MIN(MAX(0,C38-F38),MAX(0,IF(A38>=$C$13,$C$12,0)+SUMIF($E$5:$E$14,A38,$F$5:$F$14))),2)) -> 200 | H38: =ROUND(E38+G38,2) -> 2132.9 | I38: =ROUND(C38-F38-G38,2) -> 295502.7 | J38: =ROUND(J37+D38,2) -> 10433 | K38: =ROUND(K37+F38+G38,2) -> 4497.3 | M38: =Q37 -> 297369.92 | N38: =ROUND(M38*$C$16,2) -> 1486.85 | O38: =IF(M38<=0,0,ROUND(CHOOSE($C$10,IF(A38=$C$17,M38+N38,MIN($C$18,M38+N38)),IF(A38=$C$17,M38,MIN($C$19,M38))+N38,IF(A38=$C$17,M38,0)+N38),2)) -> 1932.9 | P38: =IF(M38<=0,0,MAX(0,ROUND(O38-N38,2))) -> 446.05 | Q38: =ROUND(M38-P38,2) -> 296923.87
A39: =A38+1 -> 8 | B39: =IF(MOD(12,$C$7)=0,EDATE($C$9,(A39-1)*12/$C$7),$C$9+(A39-1)*ROUND(364/$C$7,0)) -> 46539 | C39: =I38 -> 295502.7 | D39: =ROUND(C39*$C$16,2) -> 1477.51 | E39: =IF(C39<=0,0,ROUND(CHOOSE($C$10,IF(A39=$C$17,C39+D39,MIN($C$18,C39+D39)),IF(A39=$C$17,C39,MIN($C$19,C39))+D39,IF(A39=$C$17,C39,0)+D39),2)) -> 1932.9 | F39: =IF(C39<=0,0,MAX(0,ROUND(E39-D39,2))) -> 455.39 | G39: =IF(C39<=0,0,ROUND(MIN(MAX(0,C39-F39),MAX(0,IF(A39>=$C$13,$C$12,0)+SUMIF($E$5:$E$14,A39,$F$5:$F$14))),2)) -> 200 | H39: =ROUND(E39+G39,2) -> 2132.9 | I39: =ROUND(C39-F39-G39,2) -> 294847.31 | J39: =ROUND(J38+D39,2) -> 11910.51 | K39: =ROUND(K38+F39+G39,2) -> 5152.69 | M39: =Q38 -> 296923.87 | N39: =ROUND(M39*$C$16,2) -> 1484.62 | O39: =IF(M39<=0,0,ROUND(CHOOSE($C$10,IF(A39=$C$17,M39+N39,MIN($C$18,M39+N39)),IF(A39=$C$17,M39,MIN($C$19,M39))+N39,IF(A39=$C$17,M39,0)+N39),2)) -> 1932.9 | P39: =IF(M39<=0,0,MAX(0,ROUND(O39-N39,2))) -> 448.28 | Q39: =ROUND(M39-P39,2) -> 296475.59
A40: =A39+1 -> 9 | B40: =IF(MOD(12,$C$7)=0,EDATE($C$9,(A40-1)*12/$C$7),$C$9+(A40-1)*ROUND(364/$C$7,0)) -> 46569 | C40: =I39 -> 294847.31 | D40: =ROUND(C40*$C$16,2) -> 1474.24 | E40: =IF(C40<=0,0,ROUND(CHOOSE($C$10,IF(A40=$C$17,C40+D40,MIN($C$18,C40+D40)),IF(A40=$C$17,C40,MIN($C$19,C40))+D40,IF(A40=$C$17,C40,0)+D40),2)) -> 1932.9 | F40: =IF(C40<=0,0,MAX(0,ROUND(E40-D40,2))) -> 458.66 | G40: =IF(C40<=0,0,ROUND(MIN(MAX(0,C40-F40),MAX(0,IF(A40>=$C$13,$C$12,0)+SUMIF($E$5:$E$14,A40,$F$5:$F$14))),2)) -> 200 | H40: =ROUND(E40+G40,2) -> 2132.9 | I40: =ROUND(C40-F40-G40,2) -> 294188.65 | J40: =ROUND(J39+D40,2) -> 13384.75 | K40: =ROUND(K39+F40+G40,2) -> 5811.35 | M40: =Q39 -> 296475.59 | N40: =ROUND(M40*$C$16,2) -> 1482.38 | O40: =IF(M40<=0,0,ROUND(CHOOSE($C$10,IF(A40=$C$17,M40+N40,MIN($C$18,M40+N40)),IF(A40=$C$17,M40,MIN($C$19,M40))+N40,IF(A40=$C$17,M40,0)+N40),2)) -> 1932.9 | P40: =IF(M40<=0,0,MAX(0,ROUND(O40-N40,2))) -> 450.52 | Q40: =ROUND(M40-P40,2) -> 296025.07
A41: =A40+1 -> 10 | B41: =IF(MOD(12,$C$7)=0,EDATE($C$9,(A41-1)*12/$C$7),$C$9+(A41-1)*ROUND(364/$C$7,0)) -> 46600 | C41: =I40 -> 294188.65 | D41: =ROUND(C41*$C$16,2) -> 1470.94 | E41: =IF(C41<=0,0,ROUND(CHOOSE($C$10,IF(A41=$C$17,C41+D41,MIN($C$18,C41+D41)),IF(A41=$C$17,C41,MIN($C$19,C41))+D41,IF(A41=$C$17,C41,0)+D41),2)) -> 1932.9 | F41: =IF(C41<=0,0,MAX(0,ROUND(E41-D41,2))) -> 461.96 | G41: =IF(C41<=0,0,ROUND(MIN(MAX(0,C41-F41),MAX(0,IF(A41>=$C$13,$C$12,0)+SUMIF($E$5:$E$14,A41,$F$5:$F$14))),2)) -> 200 | H41: =ROUND(E41+G41,2) -> 2132.9 | I41: =ROUND(C41-F41-G41,2) -> 293526.69 | J41: =ROUND(J40+D41,2) -> 14855.69 | K41: =ROUND(K40+F41+G41,2) -> 6473.31 | M41: =Q40 -> 296025.07 | N41: =ROUND(M41*$C$16,2) -> 1480.13 | O41: =IF(M41<=0,0,ROUND(CHOOSE($C$10,IF(A41=$C$17,M41+N41,MIN($C$18,M41+N41)),IF(A41=$C$17,M41,MIN($C$19,M41))+N41,IF(A41=$C$17,M41,0)+N41),2)) -> 1932.9 | P41: =IF(M41<=0,0,MAX(0,ROUND(O41-N41,2))) -> 452.77 | Q41: =ROUND(M41-P41,2) -> 295572.3
A42: =A41+1 -> 11 | B42: =IF(MOD(12,$C$7)=0,EDATE($C$9,(A42-1)*12/$C$7),$C$9+(A42-1)*ROUND(364/$C$7,0)) -> 46631 | C42: =I41 -> 293526.69 | D42: =ROUND(C42*$C$16,2) -> 1467.63 | E42: =IF(C42<=0,0,ROUND(CHOOSE($C$10,IF(A42=$C$17,C42+D42,MIN($C$18,C42+D42)),IF(A42=$C$17,C42,MIN($C$19,C42))+D42,IF(A42=$C$17,C42,0)+D42),2)) -> 1932.9 | F42: =IF(C42<=0,0,MAX(0,ROUND(E42-D42,2))) -> 465.27 | G42: =IF(C42<=0,0,ROUND(MIN(MAX(0,C42-F42),MAX(0,IF(A42>=$C$13,$C$12,0)+SUMIF($E$5:$E$14,A42,$F$5:$F$14))),2)) -> 200 | H42: =ROUND(E42+G42,2) -> 2132.9 | I42: =ROUND(C42-F42-G42,2) -> 292861.42 | J42: =ROUND(J41+D42,2) -> 16323.32 | K42: =ROUND(K41+F42+G42,2) -> 7138.58 | M42: =Q41 -> 295572.3 | N42: =ROUND(M42*$C$16,2) -> 1477.86 | O42: =IF(M42<=0,0,ROUND(CHOOSE($C$10,IF(A42=$C$17,M42+N42,MIN($C$18,M42+N42)),IF(A42=$C$17,M42,MIN($C$19,M42))+N42,IF(A42=$C$17,M42,0)+N42),2)) -> 1932.9 | P42: =IF(M42<=0,0,MAX(0,ROUND(O42-N42,2))) -> 455.04 | Q42: =ROUND(M42-P42,2) -> 295117.26
A43: =A42+1 -> 12 | B43: =IF(MOD(12,$C$7)=0,EDATE($C$9,(A43-1)*12/$C$7),$C$9+(A43-1)*ROUND(364/$C$7,0)) -> 46661 | C43: =I42 -> 292861.42 | D43: =ROUND(C43*$C$16,2) -> 1464.31 | E43: =IF(C43<=0,0,ROUND(CHOOSE($C$10,IF(A43=$C$17,C43+D43,MIN($C$18,C43+D43)),IF(A43=$C$17,C43,MIN($C$19,C43))+D43,IF(A43=$C$17,C43,0)+D43),2)) -> 1932.9 | F43: =IF(C43<=0,0,MAX(0,ROUND(E43-D43,2))) -> 468.59 | G43: =IF(C43<=0,0,ROUND(MIN(MAX(0,C43-F43),MAX(0,IF(A43>=$C$13,$C$12,0)+SUMIF($E$5:$E$14,A43,$F$5:$F$14))),2)) -> 200 | H43: =ROUND(E43+G43,2) -> 2132.9 | I43: =ROUND(C43-F43-G43,2) -> 292192.83 | J43: =ROUND(J42+D43,2) -> 17787.63 | K43: =ROUND(K42+F43+G43,2) -> 7807.17 | M43: =Q42 -> 295117.26 | N43: =ROUND(M43*$C$16,2) -> 1475.59 | O43: =IF(M43<=0,0,ROUND(CHOOSE($C$10,IF(A43=$C$17,M43+N43,MIN($C$18,M43+N43)),IF(A43=$C$17,M43,MIN($C$19,M43))+N43,IF(A43=$C$17,M43,0)+N43),2)) -> 1932.9 | P43: =IF(M43<=0,0,MAX(0,ROUND(O43-N43,2))) -> 457.31 | Q43: =ROUND(M43-P43,2) -> 294659.95
A44: =A43+1 -> 13 | B44: =IF(MOD(12,$C$7)=0,EDATE($C$9,(A44-1)*12/$C$7),$C$9+(A44-1)*ROUND(364/$C$7,0)) -> 46692 | C44: =I43 -> 292192.83 | D44: =ROUND(C44*$C$16,2) -> 1460.96 | E44: =IF(C44<=0,0,ROUND(CHOOSE($C$10,IF(A44=$C$17,C44+D44,MIN($C$18,C44+D44)),IF(A44=$C$17,C44,MIN($C$19,C44))+D44,IF(A44=$C$17,C44,0)+D44),2)) -> 1932.9 | F44: =IF(C44<=0,0,MAX(0,ROUND(E44-D44,2))) -> 471.94 | G44: =IF(C44<=0,0,ROUND(MIN(MAX(0,C44-F44),MAX(0,IF(A44>=$C$13,$C$12,0)+SUMIF($E$5:$E$14,A44,$F$5:$F$14))),2)) -> 200 | H44: =ROUND(E44+G44,2) -> 2132.9 | I44: =ROUND(C44-F44-G44,2) -> 291520.89 | J44: =ROUND(J43+D44,2) -> 19248.59 | K44: =ROUND(K43+F44+G44,2) -> 8479.11 | M44: =Q43 -> 294659.95 | N44: =ROUND(M44*$C$16,2) -> 1473.3 | O44: =IF(M44<=0,0,ROUND(CHOOSE($C$10,IF(A44=$C$17,M44+N44,MIN($C$18,M44+N44)),IF(A44=$C$17,M44,MIN($C$19,M44))+N44,IF(A44=$C$17,M44,0)+N44),2)) -> 1932.9 | P44: =IF(M44<=0,0,MAX(0,ROUND(O44-N44,2))) -> 459.6 | Q44: =ROUND(M44-P44,2) -> 294200.35
... A331: =A330+1 -> 300 | B331: =IF(MOD(12,$C$7)=0,EDATE($C$9,(A331-1)*12/$C$7),$C$9+(A331-1)*ROUND(364/$C$7,0)) -> 55427 | C331: =I330 -> 0 | D331: =ROUND(C331*$C$16,2) -> 0 | E331: =IF(C331<=0,0,ROUND(CHOOSE($C$10,IF(A331=$C$17,C331+D331,MIN($C$18,C331+D331)),IF(A331=$C$17,C331,MIN($C$19,C331))+D331,IF(A331=$C$17,C331,0)+D331),2)) -> 0 | F331: =IF(C331<=0,0,MAX(0,ROUND(E331-D331,2))) -> 0 | G331: =IF(C331<=0,0,ROUND(MIN(MAX(0,C331-F331),MAX(0,IF(A331>=$C$13,$C$12,0)+SUMIF($E$5:$E$14,A331,$F$5:$F$14))),2)) -> 0 | H331: =ROUND(E331+G331,2) -> 0 | I331: =ROUND(C331-F331-G331,2) -> 0 | J331: =ROUND(J330+D331,2) -> 205217.43 | K331: =ROUND(K330+F331+G331,2) -> 300000 | M331: =Q330 -> 1926.07 | N331: =ROUND(M331*$C$16,2) -> 9.63 | O331: =IF(M331<=0,0,ROUND(CHOOSE($C$10,IF(A331=$C$17,M331+N331,MIN($C$18,M331+N331)),IF(A331=$C$17,M331,MIN($C$19,M331))+N331,IF(A331=$C$17,M331,0)+N331),2)) -> 1935.7 | P331: =IF(M331<=0,0,MAX(0,ROUND(O331-N331,2))) -> 1926.07 | Q331: =ROUND(M331-P331,2) -> 0

Sheet TVM Functions
A1: Excel TVM Functions - worked examples
A2: Excel signs: money you receive is +, money you pay is -. Rates and periods must use the same unit.
A4: Function | B4: Result | C4: What it shows
A5: Loan (uses the Loan sheet inputs)
A6: Periodic rate i | B6: =Loan!C16 -> 0.005 | C6: From the Loan sheet
A7: PMT(i, N, -P, balloon) | B7: =PMT(Loan!C16,Loan!C17,-Loan!C4,Loan!C11) -> 1932.9042 | C7: Unrounded level payment
A8: IPMT(i, 1, N, -P, balloon) | B8: =IPMT(Loan!C16,1,Loan!C17,-Loan!C4,Loan!C11) -> 1500 | C8: Interest in payment 1
A9: PPMT(i, 1, N, -P, balloon) | B9: =PPMT(Loan!C16,1,Loan!C17,-Loan!C4,Loan!C11) -> 432.9042 | C9: Principal in payment 1
A10: CUMIPMT(i, N, P, 1, p, 0) | B10: =-CUMIPMT(Loan!C16,Loan!C17,Loan!C4,1,Loan!C7,0) -> 17854.734 | C10: Interest paid in year 1 (unrounded)
A11: NPER(i, -(PMT + extra), P) | B11: =IFERROR(NPER(Loan!C16,-(Loan!C18+Loan!C12),Loan!C4,-Loan!C11),"n/a") -> 243.59204 | C11: Payments needed with the recurring extra (approx.)
A12: RATE(N, -PMT, P) | B12: =IFERROR(RATE(Loan!C17,-Loan!C18,Loan!C4,-Loan!C11)*Loan!C7,"n/a") -> 0.059999771 | C12: Rate implied by the rounded payment, x p
A13: Rates
A14: EFFECT(6%, 12) | B14: =EFFECT(0.06,12) -> 0.061677812 | C14: 6% APR compounded monthly = 6.168% EAR
A15: NOMINAL(6.168%, 12) | B15: =NOMINAL(EFFECT(0.06,12),12) -> 0.06 | C15: Back to 6.000% APR
A16: Project: -100,000 at t=0, then 25k, 35k, 40k, 35k, 30k; rate 10%
A17: Correct NPV = CF0 + NPV(10%, CF1..CF5) | B17: =-100000+NPV(0.1,25000,35000,40000,35000,30000) -> 24238.595 | C17: Excel NPV discounts its FIRST value by one period, so CF0 stays outside
A18: Common mistake: NPV(10%, CF0..CF5) | B18: =NPV(0.1,-100000,25000,35000,40000,35000,30000) -> 22035.087 | C18: Discounts everything one period too much (= correct NPV / 1.10)
A19: IRR({CF0..CF5}) | B19: =IRR({-100000,25000,35000,40000,35000,30000}) -> 0.18777806 | C19: IRR treats the first value as t = 0
